Workbook

Sheet START HERE
A1: EIP ACCEPTANCE TEST CAMPAIGN — 5th-year projects tested by 3rd-year students
A2: 1 — WHAT YOU HAVE TO DO
A3: Run every scenario in your project tab by hand, exactly as written, and record what actually happened in the RESULT, Severity, Feedback, Tester and Date columns. A scenario passes only if every expected result is obtained — if you did not see it work with your own eyes, it did not work.
A4: 2 — THE RESULT VALUES
A5: Value | B5: Use it when
A6: OK | B6: Every expected result was obtained, in order, without error. Cosmetic differences do not fail a scenario — note them in Feedback and still mark OK.
A7: Partial | B7: The feature runs but at least one expected result was not obtained. Say exactly which one in Feedback.
A8: KO | B8: The feature is there but wrong: crash, wrong output, data loss, corrupted result, expected behaviour missing.
A9: Blocked | B9: You could not run the scenario at all — a prerequisite could not be met, an earlier scenario failed, the app will not start, the feature is unreachable.
A10: N/A | B10: The scenario genuinely does not apply to you: no NVIDIA GPU, no controller, the team declared it not testable this cycle. Always say why in Feedback.
A11: Not tested | B11: The starting value. Nothing has been done yet. Leave none of these behind at the end of your run.
A12: 3 — THE FIVE PROJECTS
A13: Project | B13: What it is | C13: Where to get it | D13: Scenarios | E13: Tab
A14: Eclyps | B14: Eclyps is a 3D non-Euclidean puzzle game taking place in a cel-shading styled world with a unique storyline. The purpose of our game is to make people experience mental madness perception while solving enigmas containing unusual perspectives and illusions. Inspired by games like Exit 8 or Superliminal, It challenges and forces players to think outside the box while exposing them more and more through each level to the symptoms of madness. | C14: https://eclypswebsite.netlify.app | D14: 45 total 15 critical | E14: Eclyps
A15: Dissonance | B15: Desktop app that applies imperceptible adversarial perturbations to audio so it can’t be exploited for AI training. Versions under test: UI v0.1.1 with bundled core v0.0.5 (branch dev). | C15: https://github.com/Dissonance-Eip/ui/releases/latest | D15: 56 total 27 critical | E15: Dissonance
A16: Pathly | B16: Pathly is a social network designed for travelers who love to plan, share, and explore It’s the perfect platform to create, collaborate, and customize trip itineraries with friends, family, or fellow adventurers. Discover trending destinations, get personalized recommendations, and share your travel experiences with a vibrant community of globetrotters. | C16: https://pathly-web-brown.vercel.app/ | D16: 36 total 26 critical | E16: Pathly
A17: Horus | B17: Version under test: Horus Beta 0.1.0. The archive carries the installer, the source the stack builds from, the desktop apps and the test corpus. No repository access is needed. | C17: https://epitechfr-my.sharepoint.com/:u:/g/personal/loup_marquez_epitech_eu/IQDSYS6FbbXXR50eb-HXaqiWAZdwJ_LRXc47EHymear3qyQ?e=8wllsu | D17: 37 total 25 critical | E17: Horus
A18: FAS | B18: FAS is a LegalTech solution that streamlines contract management, allowing users to create, fill, sign, and manage contracts anytime, anywhere. It uniquely supports and authenticates verbal agreements, a feature not found in other software. FAS also facilitates written agreements, leveraging AI for audio-based contract filling, summaries and more. | C18: https://fas-ai.net | D18: 44 total 19 critical | E18: FAS
A19: TOTAL | D19: 218 scenarios
A20: ECLYPS — setup & access (tab "Eclyps" · 45 scenarios)
A21: Access points
A22: Access point | B22: URL / command | C22: Notes
A23: Game download | B23: https://eclypswebsite.netlify.app
A24: Accounts
A25: Account type | B25: Identifier | C25: Password
A26: UE5 (Epic Games User) | B26: user@epicgames.com | C26: Epicpwd
A27: Steam User | B27: user@steam.com | C27: Steampwd
A28: DISSONANCE — setup & access (tab "Dissonance" · 56 scenarios)
A29: Test environment | B29: macOS on Apple Silicon (the release ships arm64 only), Windows 10/11 x64, or x64 Linux with AppImage support. Audio output: headphones strongly recommended — several scenarios are listening tests.
A30: Access points
A31: Access point | B31: URL / command | C31: Notes
A32: App download (all platforms) | C32: macOS .dmg (Apple Silicon only) · Windows .exe · Linux .AppImage (chmod +x first). This installer is the whole deliverable — nothing else needs building.
A33: Source repository (reference) | B33: https://github.com/Dissonance-Eip/ui | C33: For reference only — testers work from the installer above. Branch under test: dev.
A34: Accounts
A35: Account type | B35: Identifier | C35: Password
A36: None required | B36: — | C36: Dissonance is a fully offline desktop app: no sign-up, no login, no server.
A37: Test data
A38: All test audio files come from the team’s Appendix ZIP.
A39: File / item | B39: Description
A40: atp_stereo_44k.wav | B40: 30 s, 44.1 kHz, 16-bit stereo, all seven tags filled. Main file for the UI scenarios.
A41: atp_mono_48k.wav | B41: 30 s, 48 kHz, 16-bit mono, no tags. Mono + alternate sample rate + empty tag form.
A42: atp_fulltrack.wav | B42: 3:06, 44.1 kHz stereo. Processing time and A/B listening (F32, F35).
A43: atp_track_c.wav | B43: 90 s, quiet and sparse (peak −0.6 dBFS). Least masking headroom — the artefact-finder (F35).
A44: atp_track_d.wav | B44: 90 s, loud dense master (peak 0.0 dBFS). The opposite extreme (F35).
A45: atp_24bit.wav | B45: 30 s, 44.1 kHz, 24-bit stereo, plain PCM header (audioFormat 1). F48.
A46: atp_24bit_ext.wav | B46: Same audio, written as WAVE_FORMAT_EXTENSIBLE (audioFormat 65534) — the header a 24-bit DAW export uses. F48.
A47: atp_corrupt.wav | B47: Truncated file with a .wav extension. Error handling (F10, F30).
A48: atp_sample.mp3 | B48: 30 s MP3. F9 — a format the core does not parse yet.
A49: Before you start — read these
A50: • F1–F48 cover the desktop app under test. F49–F56 describe the in-app protection verification planned for a later build and are not testable this cycle — they are pre-set to N/A.
A51: PATHLY — setup & access (tab "Pathly" · 36 scenarios)
A52: Access points
A53: Access point | B53: URL / command | C53: Notes
A54: Access link | B54: https://pathly-web-brown.vercel.app/
A55: Test files to download | B55: https://drive.google.com/drive/folders/1zkOvY62Y2zB1DO4MH0k0u6xxBycU-A6P?usp=sharing
A56: Temporary email service (optional) | B56: https://yopmail.com/en/
A57: Accounts
A58: Account type | B58: Identifier | C58: Password
A59: User A | B59: Create with a unique email address during F1 | C59: Chosen by tester
A60: User B | B60: Create with a second unique email address during F1 | C60: Chosen by tester
A61: Before you start — read these
A62: • Browser sessions — keep User A and User B open in separate sessions: one regular + one private/incognito window, or two different browsers.
A63: • Tester ID — choose one unique identifier for your test run (for example AB4821). Append it to every trip, activity, expense, message/comment and other content created during the ATP.
A64: • Account usage — use the same User A / User B pair for the whole ATP execution. Do not reuse another tester’s accounts or test content.
A65: HORUS — setup & access (tab "Horus" · 37 scenarios)
A66: Test environment | B66: Windows, macOS or Linux (x86-64), with Docker Desktop or Docker Engine + Compose v2. The entire stack runs in Compose; nothing is installed on the host. Free disk: 150 GB (CPU profile) or 125 GB (GPU profile). About 16 GB host RAM. 4 CPU cores minimum, 12 or more recommended. Broadband: 25.0–26.5 GB of compressed download. Free TCP ports 3000, 8000, 8001, 8080, 15672, 5433, 5540. Allow 1.5 to 2 hours for the first run; later starts about 90 s.
A67: Access points
A68: Access point | B68: URL / command | C68: Notes
A69: Beta archive (Horus-Beta-0.1.0.zip) | B69: https://epitechfr-my.sharepoint.com/:u:/g/personal/loup_marquez_epitech_eu/IQDSYS6FbbXXR50eb-HXaqiWAZdwJ_LRXc47EHymear3qyQ?e=8wllsu | C69: Extract the archive, then run START-HERE-Windows.bat / START-HERE-macOS.command / START-HERE-Linux.sh. Detects hardware, writes .env, builds, starts and smoke-tests. See F1.
A70: Desktop application | B70: app/Horus.exe · app/Horus.app · app/Horus_0.1.0_amd64.deb | C70: Native window over the same web client. Unsigned, so expect an OS warning. See F2.
A71: Web client (main entry point) | B71: http://localhost:3000 | C71: All UI scenarios start here. /auth/register · /auth/login · /dashboard · /chat · /conversations · /knowledge-store · /tasks · /tasks/new · /admin/users · /admin/roles · /admin/agents · /admin/logs · /admin/metrics · /admin/traces (admin role only)
A72: MAS API (orchestrator) | B72: http://localhost:8000 | C72: REST + WebSocket. Swagger console at /docs — optional API checks only.
A73: Agent service | B73: http://localhost:8001 | C73: RAG pipeline worker.
A74: Knowledge Store API | B74: http://localhost:8080 | C74: REST API behind the Knowledge Store UI. Swagger at /docs — optional checks in F13 and F14.
A75: RabbitMQ management UI | B75: http://localhost:15672 | C75: Inspect the task queue (F26).
A76: PgAdmin | B76: http://localhost:5433 | C76: Inspect PostgreSQL state.
A77: RedisInsight | B77: http://localhost:5540 | C77: Inspect cache state.
A78: Test corpus (5 documents) | B78: horus/demo_assets/ inside the extracted archive | C78: Used by every Knowledge Store scenario.
A79: Accounts
A80: Account type | B80: Identifier | C80: Password
A81: Seeded admin (use FIRST) | B81: admin | C81: admin
A82: Admin | B82: horus.admin | C82: HorusATP2026!
A83: Manager | B83: horus.manager | C83: HorusATP2026!
A84: User | B84: horus.user | C84: HorusATP2026!
A85: User #2 (isolation tests) | B85: horus.user2 | C85: HorusATP2026!
A86: RabbitMQ management UI | B86: guest | C86: guest
A87: PgAdmin | B87: admin@admin.com | C87: admin
A88: Test data
A89: Test corpus at horus/demo_assets/, uploaded in scenario F12.
A90: File / item | B90: Description
A91: 1_Q4_2025_Financial_Report.md | B91: Finance — amounts ($4.2M, EUR 500K), dates (Q4 2025), people.
A92: 2_Employee_Handbook.md | B92: HR — people names, policy dates.
A93: 3_Compliance_Guidelines.md | B93: Compliance — regulation references, dates.
A94: 4_Expense_Policy.md | B94: Finance / Policy — amounts, thresholds, dates.
A95: 5_IT_Security_Policy.md | B95: IT / Security — systems, roles, dates.
A96: Before you start — read these
A97: • Account bootstrap (covered by F3, F4 and F5) — 1. Log in at http://localhost:3000/auth/login as admin / admin (MAS seeds this account at startup). 2. As that seeded admin, go to Admin > Users > Create New User and create horus.admin (admin), horus.manager (manager), horus.user (user) and horus.user2 (user). 3. Switch to horus.admin for every scenario from here on. Self-registration does NOT create an admin — a new account always gets the user role. Password policy: at least 10 characters with an uppercase, a lowercase, a digit and a special character.
A98: • Testing without an NVIDIA GPU — the installer selects a CPU profile automatically and 65 of the 68 scenarios remain validatable. F18, F19 and F20 are GPU-only and are pre-set to N/A, not failed. On CPU the chat does answer in 1 min 18 s to 1 min 41 s, but digits come out as homoglyphs and the router emits invalid JSON, so the answer fails validation. Same machine on GPU: 2 s and correct.
A99: • Reference queries — F18: "What was our Q4 2025 revenue?" (answer cites 1_Q4_2025_Financial_Report.md). F19: "Compare our Q4 spend against what the expense policy allows and flag anything out of policy." (cites BOTH 1_Q4_2025_Financial_Report.md and 4_Expense_Policy.md). F20: "What is the capital of Peru?" (the agent states it has no grounding document rather than answering). F13: smart-search with category = "Finance" (only finance documents returned).
A100: • Repeat questions are served from an exact-match Redis cache — asking the same question again returns the identical stored answer, including a wrong one. Re-testing F18–F20 needs a different wording or a cache flush.
...

Sheet Dashboard
A1: CAMPAIGN DASHBOARD — live, updates itself as the project tabs are filled in
A3: Project | B3: Scenarios | C3: Critical | D3: Not tested | E3: OK | F3: Partial | G3: KO | H3: Blocked | I3: N/A | J3: % tested | K3: % OK (of tested) | L3: Open defects
A5: Eclyps | B5: 45 | C5: =COUNTIF(Eclyps!$C$2:$C$46,"Critical feature") -> 15 | D5: =COUNTIF(Eclyps!$I$2:$I$46,"Not tested") -> 0 | E5: =COUNTIF(Eclyps!$I$2:$I$46,"OK") -> 21 | F5: =COUNTIF(Eclyps!$I$2:$I$46,"Partial") -> 1 | G5: =COUNTIF(Eclyps!$I$2:$I$46,"KO") -> 2 | H5: =COUNTIF(Eclyps!$I$2:$I$46,"Blocked") -> 0 | I5: =COUNTIF(Eclyps!$I$2:$I$46,"N/A") -> 21 | J5: =IF(B5=0,0,(B5-D5)/B5) -> 1 | K5: =IF((B5-D5-I5)=0,"—",E5/(B5-D5-I5)) -> 0.875 | L5: =F5+G5+H5 -> 3
A6: Dissonance | B6: 56 | C6: =COUNTIF(Dissonance!$C$2:$C$57,"Critical feature") -> 27 | D6: =COUNTIF(Dissonance!$I$2:$I$57,"Not tested") -> 0 | E6: =COUNTIF(Dissonance!$I$2:$I$57,"OK") -> 43 | F6: =COUNTIF(Dissonance!$I$2:$I$57,"Partial") -> 0 | G6: =COUNTIF(Dissonance!$I$2:$I$57,"KO") -> 0 | H6: =COUNTIF(Dissonance!$I$2:$I$57,"Blocked") -> 0 | I6: =COUNTIF(Dissonance!$I$2:$I$57,"N/A") -> 13 | J6: =IF(B6=0,0,(B6-D6)/B6) -> 1 | K6: =IF((B6-D6-I6)=0,"—",E6/(B6-D6-I6)) -> 1 | L6: =F6+G6+H6 -> 0
A7: Pathly | B7: 36 | C7: =COUNTIF(Pathly!$C$2:$C$37,"Critical feature") -> 26 | D7: =COUNTIF(Pathly!$I$2:$I$37,"Not tested") -> 0 | E7: =COUNTIF(Pathly!$I$2:$I$37,"OK") -> 30 | F7: =COUNTIF(Pathly!$I$2:$I$37,"Partial") -> 2 | G7: =COUNTIF(Pathly!$I$2:$I$37,"KO") -> 1 | H7: =COUNTIF(Pathly!$I$2:$I$37,"Blocked") -> 0 | I7: =COUNTIF(Pathly!$I$2:$I$37,"N/A") -> 3 | J7: =IF(B7=0,0,(B7-D7)/B7) -> 1 | K7: =IF((B7-D7-I7)=0,"—",E7/(B7-D7-I7)) -> 0.90909091 | L7: =F7+G7+H7 -> 3
A8: Horus | B8: 37 | C8: =COUNTIF(Horus!$C$2:$C$38,"Critical feature") -> 25 | D8: =COUNTIF(Horus!$I$2:$I$38,"Not tested") -> 0 | E8: =COUNTIF(Horus!$I$2:$I$38,"OK") -> 28 | F8: =COUNTIF(Horus!$I$2:$I$38,"Partial") -> 3 | G8: =COUNTIF(Horus!$I$2:$I$38,"KO") -> 6 | H8: =COUNTIF(Horus!$I$2:$I$38,"Blocked") -> 0 | I8: =COUNTIF(Horus!$I$2:$I$38,"N/A") -> 0 | J8: =IF(B8=0,0,(B8-D8)/B8) -> 1 | K8: =IF((B8-D8-I8)=0,"—",E8/(B8-D8-I8)) -> 0.75675676 | L8: =F8+G8+H8 -> 9
A9: FAS | B9: 44 | C9: =COUNTIF(FAS!$C$2:$C$45,"Critical feature") -> 19 | D9: =COUNTIF(FAS!$I$2:$I$45,"Not tested") -> 0 | E9: =COUNTIF(FAS!$I$2:$I$45,"OK") -> 26 | F9: =COUNTIF(FAS!$I$2:$I$45,"Partial") -> 3 | G9: =COUNTIF(FAS!$I$2:$I$45,"KO") -> 1 | H9: =COUNTIF(FAS!$I$2:$I$45,"Blocked") -> 0 | I9: =COUNTIF(FAS!$I$2:$I$45,"N/A") -> 14 | J9: =IF(B9=0,0,(B9-D9)/B9) -> 1 | K9: =IF((B9-D9-I9)=0,"—",E9/(B9-D9-I9)) -> 0.86666667 | L9: =F9+G9+H9 -> 4
A10: TOTAL | B10: =SUM(B5:B9) -> 218 | C10: =SUM(C5:C9) -> 112 | D10: =SUM(D5:D9) -> 0 | E10: =SUM(E5:E9) -> 148 | F10: =SUM(F5:F9) -> 9 | G10: =SUM(G5:G9) -> 10 | H10: =SUM(H5:H9) -> 0 | I10: =SUM(I5:I9) -> 51 | J10: =IF(B10=0,0,(B10-D10)/B10) -> 1 | K10: =IF((B10-D10-I10)=0,"—",E10/(B10-D10-I10)) -> 0.88622754 | L10: =SUM(L5:L9) -> 19
A12: Open defects = Partial + KO + Blocked. "% OK (of tested)" excludes rows marked N/A. All figures recalculate automatically — nothing here is typed by hand.
A14: CRITICAL FEATURES ONLY — the scenarios that decide whether the product works at all
A15: Project | B15: Critical | C15: Not tested | D15: OK | E15: Partial | F15: KO | G15: Blocked | H15: N/A | I15: % critical tested | J15: % critical OK
A16: Eclyps | B16: =COUNTIF(Eclyps!$C$2:$C$46,"Critical feature") -> 15 | C16: =COUNTIFS(Eclyps!$C$2:$C$46,"Critical feature",Eclyps!$I$2:$I$46,"Not tested") -> 0 | D16: =COUNTIFS(Eclyps!$C$2:$C$46,"Critical feature",Eclyps!$I$2:$I$46,"OK") -> 11 | E16: =COUNTIFS(Eclyps!$C$2:$C$46,"Critical feature",Eclyps!$I$2:$I$46,"Partial") -> 1 | F16: =COUNTIFS(Eclyps!$C$2:$C$46,"Critical feature",Eclyps!$I$2:$I$46,"KO") -> 0 | G16: =COUNTIFS(Eclyps!$C$2:$C$46,"Critical feature",Eclyps!$I$2:$I$46,"Blocked") -> 0 | H16: =COUNTIFS(Eclyps!$C$2:$C$46,"Critical feature",Eclyps!$I$2:$I$46,"N/A") -> 3 | I16: =IF(B16=0,0,(B16-C16)/B16) -> 1 | J16: =IF((B16-C16-H16)=0,"—",D16/(B16-C16-H16)) -> 0.91666667
A17: Dissonance | B17: =COUNTIF(Dissonance!$C$2:$C$57,"Critical feature") -> 27 | C17: =COUNTIFS(Dissonance!$C$2:$C$57,"Critical feature",Dissonance!$I$2:$I$57,"Not tested") -> 0 | D17: =COUNTIFS(Dissonance!$C$2:$C$57,"Critical feature",Dissonance!$I$2:$I$57,"OK") -> 21 | E17: =COUNTIFS(Dissonance!$C$2:$C$57,"Critical feature",Dissonance!$I$2:$I$57,"Partial") -> 0 | F17: =COUNTIFS(Dissonance!$C$2:$C$57,"Critical feature",Dissonance!$I$2:$I$57,"KO") -> 0 | G17: =COUNTIFS(Dissonance!$C$2:$C$57,"Critical feature",Dissonance!$I$2:$I$57,"Blocked") -> 0 | H17: =COUNTIFS(Dissonance!$C$2:$C$57,"Critical feature",Dissonance!$I$2:$I$57,"N/A") -> 6 | I17: =IF(B17=0,0,(B17-C17)/B17) -> 1 | J17: =IF((B17-C17-H17)=0,"—",D17/(B17-C17-H17)) -> 1
A18: Pathly | B18: =COUNTIF(Pathly!$C$2:$C$37,"Critical feature") -> 26 | C18: =COUNTIFS(Pathly!$C$2:$C$37,"Critical feature",Pathly!$I$2:$I$37,"Not tested") -> 0 | D18: =COUNTIFS(Pathly!$C$2:$C$37,"Critical feature",Pathly!$I$2:$I$37,"OK") -> 23 | E18: =COUNTIFS(Pathly!$C$2:$C$37,"Critical feature",Pathly!$I$2:$I$37,"Partial") -> 2 | F18: =COUNTIFS(Pathly!$C$2:$C$37,"Critical feature",Pathly!$I$2:$I$37,"KO") -> 1 | G18: =COUNTIFS(Pathly!$C$2:$C$37,"Critical feature",Pathly!$I$2:$I$37,"Blocked") -> 0 | H18: =COUNTIFS(Pathly!$C$2:$C$37,"Critical feature",Pathly!$I$2:$I$37,"N/A") -> 0 | I18: =IF(B18=0,0,(B18-C18)/B18) -> 1 | J18: =IF((B18-C18-H18)=0,"—",D18/(B18-C18-H18)) -> 0.88461538
A19: Horus | B19: =COUNTIF(Horus!$C$2:$C$38,"Critical feature") -> 25 | C19: =COUNTIFS(Horus!$C$2:$C$38,"Critical feature",Horus!$I$2:$I$38,"Not tested") -> 0 | D19: =COUNTIFS(Horus!$C$2:$C$38,"Critical feature",Horus!$I$2:$I$38,"OK") -> 21 | E19: =COUNTIFS(Horus!$C$2:$C$38,"Critical feature",Horus!$I$2:$I$38,"Partial") -> 0 | F19: =COUNTIFS(Horus!$C$2:$C$38,"Critical feature",Horus!$I$2:$I$38,"KO") -> 4 | G19: =COUNTIFS(Horus!$C$2:$C$38,"Critical feature",Horus!$I$2:$I$38,"Blocked") -> 0 | H19: =COUNTIFS(Horus!$C$2:$C$38,"Critical feature",Horus!$I$2:$I$38,"N/A") -> 0 | I19: =IF(B19=0,0,(B19-C19)/B19) -> 1 | J19: =IF((B19-C19-H19)=0,"—",D19/(B19-C19-H19)) -> 0.84
A20: FAS | B20: =COUNTIF(FAS!$C$2:$C$45,"Critical feature") -> 19 | C20: =COUNTIFS(FAS!$C$2:$C$45,"Critical feature",FAS!$I$2:$I$45,"Not tested") -> 0 | D20: =COUNTIFS(FAS!$C$2:$C$45,"Critical feature",FAS!$I$2:$I$45,"OK") -> 13 | E20: =COUNTIFS(FAS!$C$2:$C$45,"Critical feature",FAS!$I$2:$I$45,"Partial") -> 2 | F20: =COUNTIFS(FAS!$C$2:$C$45,"Critical feature",FAS!$I$2:$I$45,"KO") -> 0 | G20: =COUNTIFS(FAS!$C$2:$C$45,"Critical feature",FAS!$I$2:$I$45,"Blocked") -> 0 | H20: =COUNTIFS(FAS!$C$2:$C$45,"Critical feature",FAS!$I$2:$I$45,"N/A") -> 4 | I20: =COUNTIFS(FAS!$C$2:$C$45,"Critical feature",FAS!$I$2:$I$45,"N/A") -> 4 | J20: =IF((B20-C20-H20)=0,"—",D20/(B20-C20-H20)) -> 0.86666667

Sheet Eclyps
A1: Feature ID | B1: Feature Name | C1: Category | D1: Dev status (team) | E1: Objective | F1: Prerequisites | G1: Steps | H1: Expected results | I1: RESULT | J1: Severity | K1: Feedback / anomaly (what you actually saw)
A2: F1 | B2: Install Game on PC | C2: Compatibility | D2: Done | E2: Verify that the game installs correctly on a Windows PC from the provided build. | F2: Game installer/build package available; sufficient disk space; Windows 10/11 PC | G2: 1. Download or copy the installer/build package to the target PC 2. Run the installer (or extract the build) 3. Follow the on-screen installation steps 4. Launch the game shortcut/executable once installation completes | H2: Installation completes without errors, and the game shortcut/executable is created and can be launched. | I2: OK
A3: F2 | B3: Launch the Game | C3: Critical feature | D3: Done | E3: Verify that the player can launch the game and reach the main menu. | F3: Game installed | G3: 1. Double-click the game executable/shortcut 2. Wait for the game to load 3. Observe the main menu | H3: The game launches without crashing and the main menu is displayed within a reasonable loading time. | I3: OK
A4: F3 | B4: Edit Graphics Settings | C4: User interface | D4: Done | E4: Verify that the player can change graphics quality settings. | F4: Game launched, Settings menu accessible | G4: 1. Open the Settings menu (M) 2. Go to the Graphics tab 3. Change the graphics quality preset (e.g. Low/Medium/High) 4. Apply/save changes 5. Return to gameplay | H4: The selected graphics quality is applied immediately or after confirmation, and the setting persists after restarting the game. | I4: OK | K4: could have a save button frowhe editing the controls
A5: F4 | B5: Edit Resolution Settings | C5: User interface | D5: Done | E5: Verify that the player can change the screen resolution. | F5: Game launched, Settings menu accessible | G5: 1. Open the Settings menu (M) 2. Go to the Display/Graphics tab 3. Select a different resolution from the list 4. Apply the change 5. Confirm the new resolution if a confirmation prompt appears | H5: The game switches to the selected resolution correctly, without distortion, and the change persists after restart. | I5: OK
A6: F5 | B6: Edit Keybinds | C6: User interface | D6: Done | E6: Verify that the player can remap keyboard/mouse keybinds. | F6: Game launched, Settings menu accessible | G6: 1. Open the Settings menu (M) 2. Go to the Controls/Keybinds tab 3. Select an action to rebind (e.g. "Change Gravity") 4. Press a new key 5. Save changes and return to gameplay 6. Test the action in-game with the new key | H6: The action is rebound to the new key, the old key no longer triggers it, and the new binding persists after restart. | I6: OK
A7: F6 | B7: Edit Volume Settings | C7: User interface | D7: Done | E7: Verify that the player can adjust audio volume levels. | F7: Game launched, Settings menu accessible | G7: 1. Open the Settings menu (M) 2. Go to the Audio tab 3. Adjust the master/music/SFX volume sliders 4. Apply changes 5. Return to gameplay and listen for the change | H7: In-game audio volume reflects the new slider values immediately, and the settings persist after restart. | I7: OK
A8: F7 | B8: Edit Mouse/Camera Sensitivity | C8: User interface | D8: Done | E8: Verify that the player can adjust camera/mouse sensitivity. | F8: Game launched, Settings menu accessible | G8: 1. Open the Settings menu (M) 2. Go to the Controls tab 3. Adjust the mouse/camera sensitivity slider 4. Apply changes 5. Return to gameplay and move the mouse to test camera speed | H8: Camera movement speed reflects the new sensitivity value, and the setting persists after restart. | I8: OK
A9: F8 | B9: Play with a Controller | C9: Compatibility | D9: Done | E9: Verify that the player can play the game using a controller. | F9: Compatible controller connected (wired or wireless) before or during launch | G9: 1. Connect a controller to the PC 2. Launch or resume the game 3. Move the character and camera using the controller sticks 4. Trigger core actions (interact, gravity change, menu navigation) using controller buttons | H9: The game detects the controller automatically, on-screen prompts switch to controller icons, and all core actions respond correctly to controller input. | I9: N/A | K9: i dont have a controller
A10: F9 | B10: Play with Keyboard & Mouse | C10: Compatibility | D10: Done | E10: Verify that the player can play the game using keyboard and mouse. | F10: Keyboard and mouse connected | G10: 1. Launch or resume the game with keyboard and mouse connected 2. Move the character using the keyboard 3. Look around using the mouse 4. Trigger core actions (interact (E), gravity change (G)) using keyboard/mouse inputs | H10: Character movement, camera look, and all core actions respond correctly to keyboard and mouse input, with on-screen prompts showing keyboard/mouse icons. | I10: OK
A11: F10 | B11: Change Gravity Manually | C11: Critical feature | D11: Done | E11: Verify that the player can change gravity direction using a dedicated key. | F11: Player in an open area with enough space to fall/land after a gravity change | G11: 1. Stand in an open area 2. Press the "Change Gravity" key (G) 3. Observe the character reorient and fall toward the new "down" direction 4. Repeat in a different direction | H11: Gravity direction changes instantly and consistently in the chosen direction, the character re-orients and falls correctly, with no clipping or getting stuck. | I11: OK
A12: F11 | B12: Trigger Gravity Change Through a Zone | C12: Critical feature | D12: Done | E12: Verify that gravity changes automatically when the player enters a designated trigger zone. | F12: Level section containing a gravity-trigger zone | G12: 1. Walk toward the trigger zone 2. Fully enter the zone 3. Observe gravity direction change automatically 4. Walk out of the zone and confirm gravity behavior afterward | H12: Gravity reorients automatically and smoothly as soon as the player enters the trigger zone, matching the zone's designated direction. | I12: OK
A13: F12 | B13: Run through Infinite Structure | C13: Critical feature | D13: Done | E13: Verify that the player can ascend or descend a staircase that loops infinitely. | F13: Level section containing the infinite stairs puzzle | G13: 1. Approach the character to interact with him (teleported to the stairs) 2. Walk up the stairs continuously for multiple flights 3. Walk down the stairs continuously for multiple flights 4. Observe the loop behavior and any visual cues | H13: The staircase loops seamlessly with no visible seams, loading hitches, or breaks in geometry while walking up or down. | I13: OK
A14: F13 | B14: Enter a Face of the Cube | C14: Critical feature | D14: Done | E14: Verify that the player can walk into a face of the non-euclidean cube and enter its interior space. | F14: Player standing next to the non-euclidean cube | G14: 1. Open the Level Menu with L keybind 2. Select the Cube Menu 3. Approach one face of the cube 4. Walk into the face 5. Observe the transition into the interior space | H14: The player enters the cube's interior smoothly, with a seamless transition and no camera clipping. | I14: OK
A15: F14 | B15: Resize Object via Forced Perspective | C15: Critical feature | D15: Done | E15: Verify that the player can change an object's apparent (and functional) size based on camera perspective. | F15: Level section containing a forced-perspective object | G15: 1. Target a holdable item with the crossair 2. Hold the left mouse button to pick it up 3. Look around to resize it (up for it to get bigger, down for smaller) 4. Pick up or release the object at the desired size | H15: The object's effective size updates according to the player's perspective, and the resized state is applied correctly when the illusion is "locked in". | I15: OK
A16: F15 | B16: Traverse a Seamless Portal | C16: Critical feature | D16: Done | E16: Verify that the player can walk through a portal and be seamlessly transported to the linked location. | F16: Level section containing a pair of linked portals | G16: 1. Approach the portal 2. See the other side (where you'll be teleported) through it 3. Walk through it 4. Observe the transition to the linked location 5. Confirm player position, velocity, and camera orientation after the transition | H16: The player is transported instantly and seamlessly, momentum and orientation are preserved correctly, with no loading pause or visual pop. | I16: OK
A17: F16 | B17: Save Game | C17: Critical feature | D17: Done | E17: Verify that the player can save game progress. | F17: Player has made progress in a level; save menu accessible | G17: 1. Open the pause/save menu (Through Main Menu accessed by M keybind) 2. Select "Save Game" 3. Choose a save slot (new or existing) 4. Confirm the save | H17: A confirmation message is shown, and a save file is created/updated with the player's current progress. | I17: OK
A18: F17 | B18: Load Game | C18: Critical feature | D18: Done | E18: Verify that the player can load a previously saved game. | F18: At least one save file exists | G18: 1. From the main menu or pause menu (M keybind), select "Load Game" 2. Choose a save slot 3. Confirm loading | H18: The game restores the player's exact saved state (position, inventory, level progress) without errors. | I18: OK
A19: F18 | B19: Interact with an Element | C19: Critical feature | D19: Done | E19: Verify that the player can interact with interactive objects in the environment. | F19: Level section containing multiple interactive objects (doors, switches, items) | G19: 1. Approach an interactive object 2. Hover the item to display interaction popup 3. Press the interact key/button indicated 4. Observe the resulting action | H19: Each interactive object responds correctly to the interact input (opens, activates, picked up, etc.) with no missed inputs. The instruction pop up should be displayed at step 2. | I19: Partial | K19: i can no clip on some parts of the house in lvl1 (the kitchen)
A20: F19 | B20: Reconstruct Projection into 3D Object | C20: Critical feature | D20: Done | E20: Verify that the player can turn a 2D wall projection into a real 3D object. | F20: A valid 2D projection is currently visible on a wall | G20: 1. Approach the 2D projection on the wall 2. Put yourself in the alignment of the projection to recompose the object 3. Observe the projection becoming a physical 3D object 4. Interact with the reconstructed item | H20: The 2D projection correctly converts into a solid, physically-present 3D object matching its projected shape. | I20: OK
A21: F20 | B21: Control the Day/Night Cycle | C21: Secondary function | D21: In progress | E21: Verify that the player can control the progression of the day/night cycle. | F21: Level section supporting the day/night cycle mechanic | G21: 1. Accelerate the day/night control (N) 2. Observe the lighting transition from day to night (or vice versa) 3. Confirm gameplay elements tied to the cycle react accordingly (not applicable yet) | H21: The lighting and sky transition smoothly between day and night when triggered, and the change is visually consistent across the scene. | I21: KO | K21: button doesnt work and cannot change it in the controls
A22: F21 | B22: Open & Close the Inventory | C22: User interface | D22: Done | E22: Verify that the player can open and close the inventory screen. | F22: Player has at least one item, or an empty inventory is accessible | G22: 1. Press the inventory key/button (I) 2. Observe the inventory screen opening 3. Press the key/button again to close it | H22: The inventory opens and closes smoothly without unexpectedly breaking other systems, and displays the correct current items. | I22: OK
A23: F22 | B23: Equip, Use and Combine Items | C23: Critical feature | D23: Done | E23: Verify that items picked up in the world are correctly added to the inventory. | F23: A pickupable item present in the level | G23: 1. Approach the plane piece in the barn 2. Press the interact/pick-up key (P) 3. Open the inventory and confirm the item appears 4) Drag the item and drop it in the first hotbar slot 5) Activate the hotbar slot pressing (1) 6) Equip item in hand using (W) 7) In the barn go close to the plane and press P to place (use) the item | H23: The item disappears from the world and appears correctly in the inventory with the correct icon/name. | I23: OK
A24: F23 | B24: Toggle Object Visibility | C24: Secondary function | D24: Done | E24: Verify that the player can toggle the visibility of certain objects using the visibility switch mechanic. | F24: Level section containing objects affected by the visibility switch | G24: 1. Go in a Visibility Zone (plateforms are in there) 2. Press E key to toggle on or off visiblity 3. Observe affected objects becoming visible or invisible 4. Toggle again and confirm objects revert | H24: Affected objects reliably switch between visible and invisible states, and their collision state updates consistently with their visibility (if intended). | I24: N/A | K24: could not access it
A25: F24 | B25: Crossing a Color Portal | C25: Secondary function | D25: Done | E25: Verify that the game's color grading evolves as intended (e.g. across levels or story progression). | F25: Progress through at least two areas/levels with different intended color styles | G25: 1. Approach a color portal 2.See the color changing through the portal 3. Cross the color portal 4. Observe the color grading change | H25: The color grading transitions smoothly and clearly reflects the intended visual evolution between areas or story beats. | I25: OK
A26: F25 | B26: View & Skip a Cinematic | C26: User interface | D26: Done | E26: Verify that story cinematics play correctly and return control to the player afterward. | F26: Level section that triggers a cinematic | G26: 1. Reach the trigger point for the cinematic by opening Showroom map 2. Let the cinematic play through fully 3. Confirm control returns to the player afterward 4. Repeat step 1 to 3 but hold Space to skip cinematic | H26: The cinematic plays without stutter or audio desync, and gameplay control is returned smoothly once it ends. | I26: N/A | K26: could not access it
A27: F26 | B27: Retry a Failed Puzzle Attempt | C27: Secondary function | D27: Done | E27: Verify that the player can retry a puzzle after an incorrect attempt without needing to restart the level. | F27: An incorrect combination/attempt has just been made on a puzzle | G27: 1. Attempt the puzzle and fail it 2. Observe the failure feedback 3. Attempt the puzzle again and win it to see the win condition | H27: The puzzle resets its interactive state after a failed attempt and can be immediately retried without a reload or crash. | I27: N/A | K27: could not access it
A28: F27 | B28: Activate a Pressure Plate | C28: Secondary function | D28: Done | E28: Verify that pressure plates correctly detect weight and trigger their linked mechanism. | F28: Level section containing a pressure plate and a linked mechanism (door, platform, etc.) | G28: 1. Step onto the pressure plate 2. Observe the linked mechanism activating (Door should open) 3. Step off the plate and observe whether the mechanism deactivates | H28: The pressure plate reliably detects the player and triggers the linked mechanism correctly each time. | I28: OK
A29: F28 | B29: Connect Cables (Snake-Style Mini-Game) | C29: Secondary function | D29: Done | E29: Verify that the player can complete the cable-connection mini-game to link two points. | F29: Level section containing a cable-connection puzzle | G29: 1. Interact with the cable puzzle to start it (E key) 2. Route the cable from the start point to the end point, avoiding obstacles (Navigating with movement keybinds) 3. Confirm the connection once the endpoint is reached | H29: The cable can be routed successfully to the endpoint, obstacles block invalid paths as intended, and a successful connection triggers the correct outcome. | I29: N/A | K29: could not access it
A30: F29 | B30: Switch to Third-Person Camera | C30: User interface | D30: Done | E30: Verify that the player can switch between first-person and third-person camera views. | F30: Player in an open area | G30: 1. Press the camera-toggle key/button (B) 2. Observe the camera switching to third-person 3. Move the character and camera to confirm normal behavior 4. Press B again to see the other point of view 4. Toggle back to first-person and confirm the switch (J) | H30: The camera switches cleanly between views with no clipping through the character or environment, and character control remains responsive in both modes. | I30: KO | K30: i cant toggle perspective
A31: F30 | B31: Capture Content with the Viewfinder | C31: Secondary function | D31: In progress | E31: Verify that the player can use the viewfinder to "capture" content from the game world. | F31: Level section supporting the viewfinder mechanic; a capturable object/scene in view | G31: 1. Take a picture with the camera item 2. Aim it at a capturable object or scene 3. Trigger the capture action 4. Confirm the captured content is stored (e.g. as a photo/item) | H31: The targeted content is correctly captured and stored, with clear visual/audio feedback confirming the capture. | I31: N/A | K31: Feature not implemented yet
A32: F31 | B32: Place the Photo Item into the Game | C32: Secondary function | D32: In progress | E32: Verify that previously captured photo content can be brought back into the game world as a real object. | F32: At least one piece of content has been captured with the viewfinder | G32: 1. Equip the photo Item in hand 2. Aim at a valid placement location 3. Trigger the placement action 4. Confirm the objects in the picture appears physically in the world | H32: The captured content materializes as a real, physically-present object at the targeted location, matching its captured appearance. | I32: N/A | K32: Feature not implemented yet
A33: F32 | B33: Interact with Tutorial Book | C33: User interface | D33: Not started | E33: Verify that the tutorial book teaches core controls correctly via its illustrated pages. | F33: Start of Chapter 1, player at the beginning of the bedroom scene | G33: 1. Approach the open book on the floor 2. Turn through its pages clicking next button 3. Observe the drawn control prompts (e.g. the stick-figure jumping on Space) 4. Close/put away the book once finished | H33: Each page displays the correct control prompt with a clear illustrated demonstration, and closing the book returns control to the player without issues. | I33: N/A | K33: Feature not implemented yet
A34: F33 | B34: Locate the Rocket Ship constellation | C34: Secondary function | D34: Not started | E34: Verify that looking through the telescope reveals the rocket-shaped constellation clue. | F34: Player is near the telescope in the bedroom | G34: 1. Interact with the telescope (E) to look through it 2. Observe the night sky view 3. Identify the rocket-shaped constellation | H34: The telescope view clearly displays a constellation shaped like the rocket, providing a legible clue toward the rocket toy. | I34: N/A | K34: Feature not implemented yet
A35: F34 | B35: Complete the "Find Jack" Enigma | C35: Critical feature | D35: Not started | E35: Verify that the player can complete the full "Find Jack" sequence from the locked door to retrieving the plushie. | F35: Player has explored the bedroom and identified the rocket toy as the point of interest | G35: 1. Attempt to open the bedroom door and observe it is locked 2. Enter the rocket toy by stepping through it's door 3. Observe the seamless transition into its giant imaginary interior 4. Complete the platformer section (bouncy plushie floor, moving platforms) to reach the top 5. Retrieve Jack, who is glowing at the top 6. Exit the rocket and observe it return to its small toy state 7. Open the now-unlocked bedroom door | H35: The entire sequence completes without errors: the transition into the rocket is seamless, the platformer section is completable without softlocks, Jack is correctly retrieved, and the door unlocks only after Jack is obtained. | I35: N/A | K35: Feature not implemented yet
A36: F35 | B36: Find Clothes Enigma | C36: Secondary function | D36: Not started | E36: Verify that the player can find and put on clothes before heading outside. | F36: Breakfast scene completed, mother has asked Céleste to get dressed | G36: 1. Explore the house to locate the clothes 2. Interact (E key) with the clothes to collect/equip them 3. Confirm Céleste is now dressed | H36: The clothes can be found through normal exploration, and once collected, the character model updates and the path outside becomes accessible. | I36: N/A | K36: Feature not implemented yet
A37: F36 | B37: Pilot the Plane during Flight Sequence | C37: Secondary function | D37: Not started | E37: Verify that the player can pilot the plane through the imaginary flight sequence. | F37: Plane repair puzzle completed, Céleste seated in the pilot's seat | G37: 1. Take control of the plane in the dream sequence 2. Steer to avoid obstacles 3. Fly through the luminous circles 4. Reach the end of the sequence | H37: The plane responds correctly to steering input, obstacles and circles register collisions/passes correctly, and the sequence ends cleanly back in reality. | I37: N/A | K37: Feature not implemented yet
A38: F37 | B38: Exit the Infinite Corridor Loop | C38: Critical feature | D38: Not started | E38: Verify that the hospital corridor loops infinitely when no valid exit condition has been met. | F38: Player is in the looping corridor segment, without the correct code/condition | G38: 1. Walk the corridor to its apparent end 2. Continue forward 3. Observe the corridor looping back to a previous or equivalent point 4. Repeat the loop at least twice 5. Spot a difference to break the loop 6. End the level by spotting the differences and escape all corridors | H38: The corridor loops seamlessly with no visible seam, loading hitch, or way to bypass it without meeting the exit condition. | I38: N/A | K38: Feature not implemented yet
A39: F38 | B39: Control the time | C39: Secondary function | D39: Not started | E39: Verify that the player can use directional movement to advance or rewind time in the maze, correctly moving objects around them. | F39: Player is in the Chapter 3 forest-approach maze sequence, following the star | G39: 1. Move in the "left" direction and observe time advancing (objects/obstacles shifting position accordingly) 2. Move in the opposite direction and observe time rewinding (objects/obstacles returning to prior positions) 3. Alternate directions to navigate around an obstacle that only allows passage at a specific point in time 4. Reach the end of the path using the time manipulation | H39: Moving in one direction consistently advances time and moving in the opposite direction consistently rewinds it, with surrounding objects updating position accordingly in both cases, and the maze is completable using this mechanic. | I39: N/A | K39: Feature not implemented yet
A40: F39 | B40: Request a Hint | C40: User interface | D40: Not started | E40: Verify that Jack the plushie provides hints, including prompting the player to use the day/night key. | F40: Player is in the forest with Jack equipped | G40: 1. Remain idle or stuck for a period 2. Observe Jack's hint behavior (glow/phosphorescence) 3. Observe the prompt suggesting the way to solve the enigma | H40: Jack's hint cues trigger appropriately without being intrusive, and the day/night key prompt is clear and correctly tied to the current situation. | I40: N/A | K40: Feature not implemented yet
... A46: F45 | B46: Complete Cube Quest | C46: Critical feature | D46: Not started | E46: Verify that the player can complete the Rocket by picking up pieces in each face of the cube | F46: Player has entered each face of the lake cube | G46: 1. Navigate each face of the cube 2. Solve enigmas of every face 3. Pick up and store every piece in inventory 4. Go outside of the cube 5. Look for the assembly zone of the rocket 6. Place the pieces of the rocket to solve the quest | H46: The scale and navigation puzzle is completable without collision errors, and the reactor piece is correctly added to the player's collected items once retrieved. | I46: N/A | K46: Feature not implemented yet

Sheet Pathly
A1: Feature ID | B1: Feature Name | C1: Category | D1: Dev status (team) | E1: Objective | F1: Prerequisites | G1: Steps | H1: Expected results | I1: RESULT | J1: Severity | K1: Feedback / anomaly (what you actually saw)
A2: F1 | B2: Sign Up | C2: Critical feature | D2: Done | E2: Verify that a visitor can create two independent Pathly accounts for collaborative testing. | F2: Pathly is accessible from the Access link in the first tab. The tester has access to two different email addresses that are not already registered in Pathly. The optional temporary email service in the first tab may be used if appropriate. | G2: 1. Choose and note a unique Tester ID (for example AB4821) for this ATP run. 2. In a regular browser session, open the Pathly Access link and navigate to Sign up. 3. Create User A with a unique email address and a password chosen by the tester. 4. Complete any email/authentication verification requested and confirm that Pathly opens while authenticated. 5. Keep User A signed in. 6. Open a private/incognito window or a second browser and navigate to Sign up. 7. Create User B using a different unique email address and a password chosen by the tester. 8. Complete any verification requested and confirm that User B can access Pathly. 9. Keep both accounts available in their separate browser sessions for the following scenarios. | H2: Two distinct Pathly accounts are created without blocking errors. User A and User B can access the authenticated platform independently in separate browser sessions. | I2: OK
A3: F2 | B3: Log in and log out | C3: Critical feature | D3: Done | E3: Verify that an existing user can authenticate and securely end the session. | F3: User A and User B were created during F1. The tester knows the credentials for both accounts and has two separate browser sessions available. | G3: 1. Log out User A from the regular browser session. 2. Log in again using the User A credentials created during F1. 3. Confirm that the authenticated interface and sidebar are displayed. 4. Log out User B from the second/private browser session. 5. Log in again using the User B credentials created during F1. 6. Confirm that the authenticated interface is displayed for User B. 7. Leave User A and User B logged in in their separate sessions for the following scenarios. | H3: Both tester-created accounts can log out and authenticate again successfully, and each account remains isolated in its own browser session. | I3: OK
A4: F3 | B4: View and navigate trips from home | C4: Critical feature | D4: Done | E4: Verify that User A can view, search, filter and open their trips from Home. | F4: User A is logged in. Complete F4 first so that 'ATP Planned Trip - [Tester ID]' is available in User A's account. | G4: 1. Open Home as User A. 2. Verify the current/upcoming trip visualization. 3. Use the top-right view control to switch to the alternative trip list view. 4. Switch between Upcoming and Past trips. 5. Search for 'ATP Planned Trip - [Tester ID]'. 6. Use a trip card action shortcut such as Calendar, Chat, Files or Gallery. 7. Return to Home and open the trip by selecting its card. | H4: Trip views load correctly, filters and search update the displayed trips, card shortcuts open the expected section, and selecting a trip card opens the correct trip overview. | I4: Partial | J4: Minor | K4: Once you close the home sidebar, there's no way to open it again.
A5: F4 | B5: Create a planned trip | C5: Critical feature | D5: Done | E5: Verify that User A can create a trip when the destination and travel dates are already known. | F5: User A is logged in. A valid future date range and a cover image from the Test Files folder are available. A unique Tester ID was chosen in F1. | G5: 1. Open Create. 2. Select Planned Trip. 3. Enter the trip name 'ATP Planned Trip - [Tester ID]' using the Tester ID chosen in F1. 4. Set a destination such as Paris, France. 5. Select a valid future date range of at least 3 days. 6. Add a short description. 7. Continue to Friends & Cover and select/upload a cover image if requested. 8. Review the information. 9. Create the trip. 10. Return to Home and locate 'ATP Planned Trip - [Tester ID]'. | H5: The Planned Trip is created with the entered information, its overview opens successfully, and the trip remains visible from Home after a page reload. | I5: OK
A6: F5 | B6: Create an open trip | C6: Critical feature | D6: Done | E6: Verify that User A can create a trip whose destination and dates will be decided collaboratively. | F6: User A is logged in. A cover image from the Test Files folder is available. A unique Tester ID was chosen in F1. | G6: 1. Open Create. 2. Select Open Trip. 3. Enter the trip name 'ATP Open Trip - [Tester ID]' using the Tester ID chosen in F1, and add a short description. 4. Continue through the creation flow without selecting a final destination or travel dates. 5. Select/upload a cover image when requested. 6. Review the information. 7. Create the trip. | H6: The Open Trip is created and opens on the collaborative decision page where destinations and dates can be proposed and voted on. | I6: OK
A7: F6 | B7: Manage trip participants | C7: Critical feature | D7: Done | E7: Verify that the owner can invite another user and manage trip membership. | F7: User A and User B were created during F1 and are logged in in separate browser sessions. User A owns 'ATP Open Trip - [Tester ID]'. | G7: 1. As User A, open 'ATP Open Trip - [Tester ID]'. 2. Open the members/participants control. 3. Invite User B using the email/username of the User B account created during F1. 4. Switch to the separate User B browser session. 5. Open the trip invitation notification or invitation flow and accept/join the trip. 6. Return to User A and refresh the member list. 7. Verify that User B is listed as a member and that owner management controls are available. | H7: User B can join the trip and appears in the member list. User A retains the expected owner controls for trip participants. | I7: OK
A8: F7 | B8: Propose open trip destinations | C8: Critical feature | D8: Done | E8: Verify that trip members can submit destination proposals for an Open Trip. | F8: User A and User B are members of 'ATP Open Trip - [Tester ID]'. The trip is still in the destination/date decision stage. Use the same User A / User B pair created in F1 in separate browser sessions. | G8: 1. As User A, open 'ATP Open Trip - [Tester ID]'. 2. Select Propose destination. 3. Add 'Lisbon, Portugal'. 4. Add a second proposal such as 'Porto, Portugal'. 5. As User B, refresh/open the same trip. 6. Verify that both proposals are visible to both members. | H8: Both destination proposals are stored and displayed consistently to the trip members and are available for voting. | I8: OK
A9: F8 | B9: Propose open trip dates | C9: Critical feature | D9: Done | E9: Verify that trip members can submit possible travel date ranges for an Open Trip. | F9: User A and User B are members of 'ATP Open Trip - [Tester ID]'. The trip is still in the destination/date decision stage. Use the same User A / User B pair created in F1 in separate browser sessions. | G9: 1. Open 'ATP Open Trip - [Tester ID]'. 2. Select Propose dates. 3. Add a valid future date range of at least 3 days. 4. Add a second, different valid future date range. 5. Open the trip as the other user and refresh the page. 6. Verify that both proposed date ranges are visible. | H9: Both date proposals are stored, displayed to all trip members and available for voting. | I9: OK
A10: F9 | B10: Vote and finalize an open trip | C10: Critical feature | D10: Done | E10: Verify that members can vote on proposed destinations and dates and move the trip into the planning stage after reaching a shared decision. | F10: F7 and F8 have been completed. User A and User B are active members of 'ATP Open Trip - [Tester ID]' and can use separate sessions. | G10: 1. As User A, vote for 'Lisbon, Portugal' and one of the proposed date ranges. 2. As User B, vote for the same destination and date range. 3. Refresh both sessions and verify the winning destination/date information. 4. Complete any confirmation/acceptance required from both members. 5. Verify that the Start Planning action becomes available. 6. Start planning the trip. | H10: The selected destination and date range are reflected as the group decision and the Open Trip successfully transitions to the standard trip planning/overview state. | I10: OK
A11: F10 | B11: View trip overview | C11: Critical feature | D11: Done | E11: Verify that the trip overview displays the main planning information and provides access to the trip tools. | F11: ATP Open Trip - [Tester ID]' has been finalized through F9. User A is logged in. | G11: 1. Open 'ATP Open Trip - [Tester ID]' from Home. 2. Verify the trip title, description, destination, dates and participants. 3. Verify the planned activity count and trip progress area. 4. Verify the mini calendar. 5. Use the Chat, Expenses, Files and Gallery shortcuts and return to the overview after each check. 6. Select the mini calendar and verify that it opens the trip calendar. 7. Return to the overview. | H11: The overview shows the correct trip data and all displayed shortcuts navigate to the corresponding trip sections. | I11: OK
A12: F11 | B12: Edit trip information and visibility | C12: Critical feature | D12: Done | E12: Verify that a trip owner can edit trip properties and control public/private visibility. | F12: User A is logged in and owns 'ATP Planned Trip - [Tester ID]'. A test image is available from the Test Files folder. | G12: 1. Open 'ATP Planned Trip - [Tester ID]'. 2. Select Edit. 3. Modify the trip description. 4. Change the cover image if the edit flow allows it. 5. Save the changes. 6. Verify that the updated values are visible in the overview. 7. Use the visibility control over the cover image to make the itinerary Public. 8. Reload the page and verify that the public state is preserved. | H12: Edited trip information persists after reload and the trip can be changed to Public without a blocking error. | I12: OK
A13: F12 | B13: View and filter trip activities | C13: Critical feature | D13: Done | E13: Verify that trip members can access the complete activity list and filter activities by status. | F13: User A is logged in and 'ATP Open Trip - [Tester ID]' has been finalized. The trip contains at least two activities. If fewer than two activities exist, create simple temporary activities before continuing. | G13: 1. Open 'ATP Open Trip - [Tester ID]'. 2. Select All activities. 3. Verify that the activity cards display key information such as name, image, date/time, location, price and status when available. 4. Use the activity status filter. 5. Switch between at least two filter values. 6. Open one activity card. | H13: The list displays the trip activities, the selected filter changes the visible results correctly, and selecting a card opens the corresponding activity detail page. | I13: OK
A14: F13 | B14: Create an activity | C14: Critical feature | D14: Done | E14: Verify that a trip member can create a complete activity through the multi-step form. | F14: User A is logged in and is a member of 'ATP Open Trip - [Tester ID]'. The trip has finalized travel dates and the tester is using the Tester ID chosen in F1. | G14: 1. Open 'ATP Open Trip - [Tester ID]'. 2. Select Add activity. 3. Enter the name 'ATP Museum Visit - [Tester ID]'. 4. Add a description and at least one tag. 5. Complete the Details & Media step with optional price/media information. 6. Set a date within the trip date range, a valid time and a location. 7. Review the activity. 8. Create it. 9. Return to the activity list. | H14: The activity is created with the entered information, appears in 'ATP Open Trip - [Tester ID]', and remains available after reloading the page. | I14: OK
A15: F14 | B15: Create an activity from saved content | C15: Critical feature | D15: Done | E15: Verify that a saved public activity can be reused to pre-fill the activity creation form. | F15: User A is logged in. Public activities created by other users are available in Explore. 'ATP Planned Trip - [Tester ID]' exists. | G15: 1. Open Explore and select Activities. 2. Open any public activity and save it. 3. Note the saved activity title. 4. Open 'ATP Planned Trip - [Tester ID]'. 5. Select Add activity. 6. Select Use saved activity. 7. Choose the activity saved in step 2. 8. Verify that the creation form is pre-filled. 9. Adjust the date/time if necessary so it fits the trip. 10. Complete the creation flow. | H15: The saved activity can be selected, its information is used to pre-fill the form, and the new activity is successfully added to 'ATP Planned Trip - [Tester ID]'. | I15: OK
A16: F15 | B16: View and manage activity details | C16: Critical feature | D16: Done | E16: Verify that activity information can be viewed, edited, have its visibility changed, and be deleted when appropriate. | F16: ATP Museum Visit - [Tester ID]' exists in 'ATP Open Trip - [Tester ID]'. User A has permission to manage the activity. | G16: 1. Open the 'ATP Museum Visit - [Tester ID]' detail page. 2. Verify its description, date, time, location, price/tags and current status. 3. Select Edit, modify the description and save. 4. Verify that the edited description persists. 5. Toggle the activity visibility between Public and Private and verify the displayed state. 6. Create a temporary activity named 'ATP Delete Test - [Tester ID]' with the minimum required information. 7. Open 'ATP Delete Test - [Tester ID]'. 8. Select Delete and confirm the action. 9. Return to the activity list. | H16: Activity details are displayed correctly, edits and visibility changes persist, and the temporary activity is removed after deletion while 'ATP Museum Visit - [Tester ID]' remains available. | I16: OK
A17: F16 | B17: Vote on an activity | C17: Critical feature | D17: Done | E17: Verify that votes from multiple trip members are stored, displayed and can change the activity status. | F17: ATP Museum Visit - [Tester ID]' exists in 'ATP Open Trip - [Tester ID]' and is Pending. User A and User B are members of the trip and are open in separate browser sessions. | G17: 1. As User A, open 'ATP Museum Visit - [Tester ID]' and vote Accept. 2. As User B, open the same activity and vote Accept. 3. Refresh the activity in both sessions. 4. Verify that both participant votes are shown and that the activity reaches the expected accepted state. 5. Change User B's vote once and verify the update. 6. Change User B's vote back to Accept so the activity finishes accepted. | H17: Both users' votes are stored and visible, changing a vote updates the displayed result, and the final activity status reflects the participants' final votes. | I17: OK
A18: F17 | B18: Organize activities with the calendar | C18: Critical feature | D18: Done | E18: Verify the calendar views and activity rescheduling rules. | F18: ATP Open Trip - [Tester ID]' contains multiple activities. 'ATP Museum Visit - [Tester ID]' is accepted after F16 and at least one activity can be rescheduled. | G18: 1. Open the Calendar for 'ATP Open Trip - [Tester ID]'. 2. Switch between Day, Week and Month views. 3. Locate 'ATP Museum Visit - [Tester ID]'. 4. Drag the accepted activity to another valid date within the trip. 5. Confirm the move if requested. 6. Verify that moving the accepted activity resets its approval/votes and requires re-approval. 7. Move a Pending activity using drag and drop. 8. Reload the calendar. | H18: All calendar views load correctly, eligible activities can be moved to valid dates, the new dates persist after reload, and moving an accepted activity applies the documented vote-reset behavior. | I18: Partial | J18: Minor | K18: Dragging an activity in the day and week calendars work perfectly and as planed, but you can't drag an activity in the month format of the calendar
A19: F18 | B19: Use trip chat | C19: Critical feature | D19: Done | E19: Verify real-time trip communication between two participants. | F19: User A and User B are members of 'ATP Open Trip - [Tester ID]' and are logged in in separate browser sessions. | G19: 1. As User A, open Messages and select the 'ATP Open Trip - [Tester ID]' conversation. 2. Send the message 'ATP chat test - [Tester ID] - from User A'. 3. As User B, open the same trip conversation. 4. Verify that User A's message is visible. 5. Send the reply 'ATP chat test - [Tester ID] - from User B'. 6. Return to User A and verify that the reply is visible. 7. Use the Trip and Activities shortcuts at the top of the chat. | H19: Messages from both users are delivered to the correct trip conversation and the chat shortcuts open the related trip overview and activity list. | I19: OK
A20: F19 | B20: Share an activity in trip chat | C20: Secondary function | D20: Done | E20: Verify that an activity can be shared as a referenced item in the trip conversation. | F20: ATP Museum Visit - [Tester ID]' exists and 'ATP Open Trip - [Tester ID]' has an active conversation with User A and User B. Use the same User A / User B pair created in F1 in separate browser sessions. | G20: 1. As User A, open the 'ATP Museum Visit - [Tester ID]' detail page. 2. Select Send to chat. 3. Open the 'ATP Open Trip - [Tester ID]' conversation. 4. Verify that the activity reference appears in the chat. 5. Open the shared activity reference from the chat if it is clickable. 6. As User B, verify that the same shared item is visible. | H20: The activity is shared in the correct trip conversation as a recognizable referenced item and is visible to the trip participants. | I20: OK
A21: F20 | B21: Manage trip and activity files | C21: Critical feature | D21: Done | E21: Verify that files attached to an activity/trip can be accessed and downloaded. | F21: User A is logged in. 'ATP Open Trip - [Tester ID]' and 'ATP Museum Visit - [Tester ID]' exist. The Test Files to download link in the first tab contains 'test-file.pdf'. | G21: 1. Open the Test Files to download link from the first tab and download 'test-file.pdf'. 2. Open the 'ATP Museum Visit - [Tester ID]' detail page. 3. Open its Files section and attach 'test-file.pdf'. 4. Verify that the file is associated with the activity. 5. Open the trip-level Files page for 'ATP Open Trip - [Tester ID]'. 6. Locate the uploaded file. 7. Download the stored file from Pathly. | H21: The test PDF can be attached to the activity, is accessible from the relevant file views, and can be downloaded successfully from Pathly. | I21: KO | J21: Major | K21: You can't add files to trips
A22: F21 | B22: Manage trip gallery and activity photos | C22: Critical feature | D22: Done | E22: Verify that trip photos can be uploaded, viewed, filtered and downloaded, and that activity photos are accessible. | F22: User A is logged in. 'ATP Open Trip - [Tester ID]' exists. The Test Files to download link contains 'test-image'. | G22: 1. Download 'test-image' from the Test Files folder in the first tab. 2. Open the Gallery for 'ATP Open Trip - [Tester ID]'. 3. Select Upload and upload the test image. 4. Associate it with a trip day/activity if that option is presented. 5. Verify that the image appears in the gallery. 6. Use the day filter and verify that the image appears in the correct result. 7. Open the image viewer. 8. Verify the displayed day/activity metadata when available. 9. Download the image from the viewer. 10. Open the linked activity and verify its Photos section if the image was associated with an activity. | H22: The image uploads successfully, appears in the correct gallery context, responds to the day filter, opens in the viewer and can be downloaded. | I22: OK
A23: F22 | B23: Manage trip expenses | C23: Critical feature | D23: Done | E23: Verify that a shared expense can be recorded with payer and split information. | F23: User A and User B are the tester-created accounts from F1, are members of 'ATP Open Trip - [Tester ID]', and are open in separate browser sessions. The test PDF is available if a receipt is desired. | G23: 1. As User A, open Expenses for 'ATP Open Trip - [Tester ID]'. 2. Select US Dollar ($) as the expense currency if necessary. 3. Select Add expense. 4. Enter description 'ATP Dinner Expense - [Tester ID]' and total amount 50.00. 5. Optionally attach 'test-file.pdf' as the receipt. 6. Set User A as the person who paid. 7. Split the expense equally between User A and User B. 8. Save the expense. 9. Verify the new expense in the expense list. | H23: The 50.00 expense is recorded with User A as payer, is split equally between the two participants, and appears in the trip expense list with the correct information. | I23: OK
A24: F23 | B24: View balances and settle expenses | C24: Critical feature | D24: Done | E24: Verify that expense balances and pending settlements are calculated and can be marked as paid. | F24: F22 has been completed using the same tester-created User A / User B pair. 'ATP Dinner Expense - [Tester ID]' is 50.00, paid by User A and split equally between User A and User B. | G24: 1. Open Expenses after F22. 2. Verify Total expenses shows 50.00 in the selected currency. 3. Verify User B owes User A 25.00 and User A gets back 25.00. 4. In User B's session, open the same Expenses page. 5. Locate the pending settlement to User A. 6. Select Mark as paid. 7. Confirm the action if requested. 8. Refresh both sessions and review balances/settlements. | H24: Before settlement, the balances reflect the 25.00 debt correctly. After marking it as paid, the pending settlement is cleared or updated and the displayed balances reflect the settlement. | I24: OK
A25: F24 | B25: Explore public itineraries and activities | C25: Critical feature | D25: Done | E25: Verify that users can discover public travel content and switch between Explore content types/feeds. | F25: User B is logged in in its separate browser session. 'ATP Planned Trip - [Tester ID]' was made Public in F11 and User B is not a member of that trip. | G25: 1. As User B, open Explore. 2. Select the Discover feed. 3. Select Trips and search for 'ATP Planned Trip - [Tester ID]'. 4. Verify that the public trip card appears and displays its main information. 5. Switch to Activities and verify public activity cards are displayed. 6. Switch to the Following feed and verify that the feed changes without an error. 7. Return to Discover. | H25: Explore displays public trips and activities according to the selected content type/feed, and 'ATP Planned Trip - [Tester ID]' is discoverable by User B while public. | I25: OK
A26: F25 | B26: Search and discover people | C26: Secondary function | D26: Done | E26: Verify that a user can search another Pathly user by username and open the result profile. | F26: User A and User B are the two accounts created during F1. User B is the active account for this scenario. | G26: 1. In a User A session, open My Profile and note User A's Pathly username. 2. As User B, open Explore. 3. Select People. 4. Enter User A's username in the search field. 5. Select the matching result. | H26: User A is returned for the username search and selecting the result opens User A's public profile. | I26: OK
A27: F26 | B27: Interact with public content | C27: Secondary function | D27: Done | E27: Verify likes, comments, saves and sharing on another user's public content. | F27: User B is logged in and can access User A's public 'ATP Planned Trip - [Tester ID]' and its public activities. | G27: 1. Open 'ATP Planned Trip - [Tester ID]' as User B. 2. Like the itinerary. 3. Add the comment 'ATP public test comment - [Tester ID]'. 4. Save the itinerary. 5. Use Share and verify that a shareable link/action is produced. 6. Open a public activity and save it so it can be used in F29. 7. Open a different public activity, save it and then unsave it to verify both states. 8. Reload the public content. | H27: Like and comment states are reflected on the public content, the itinerary and selected activity remain saved after reload, unsaving removes the second item, and the Share action works without a blocking error. | I27: OK
A28: F27 | B28: View public itinerary details | C28: Critical feature | D28: Done | E28: Verify that an external user can view the complete published itinerary and its published activities. | F28: User B is logged in. User A's 'ATP Planned Trip - [Tester ID]' is Public and contains at least one public activity. | G28: 1. Open 'ATP Planned Trip - [Tester ID]' from Explore or User A's profile. 2. Verify the title, description, destination, dates and Public itinerary indicator. 3. Verify the social actions (Like, Comment, Save, Share). 4. Scroll through the itinerary by day. 5. Verify that its published activity/activity cards are displayed with their information. 6. Select one activity and verify that the selected activity is clearly identifiable in the public itinerary view. | H28: The public itinerary is readable by User B, shows the expected public trip information and published activity content, and the selected activity can be identified from the public view. | I28: OK
A29: F28 | B29: Reuse public travel content | C29: Critical feature | D29: Done | E29: Verify that public itineraries and activities can be reused in the user's own planning. | F29: User B is logged in and can access User A's public 'ATP Planned Trip - [Tester ID]'. At least one additional public activity is available in Explore. | G29: 1. Open 'ATP Planned Trip - [Tester ID]' as User B. 2. Select Create Copy. 3. Complete the copy flow if additional information is requested. 4. Open Home and verify that the copied trip belongs to User B. 5. Return to Explore and open a different public activity. 6. Select Add to Trip. 7. Choose the copied trip created in step 2. 8. Open the copied trip and verify the added activity. | H29: User B obtains a personal copy of the public itinerary and can add another public activity to that copied trip. | I29: OK
A30: F29 | B30: View and search saved content | C30: Critical feature | D30: Done | E30: Verify that saved itineraries and activities can be found, searched and managed. | F30: User B is logged in. F26 left at least one itinerary and one activity saved in the User B account created during F1. | G30: 1. Open Saved. 2. Select Itineraries and verify that 'ATP Planned Trip - [Tester ID]' is present. 3. Search for 'ATP Planned Trip - [Tester ID]'. 4. Select Activities and verify the activity saved in F26 is present. 5. Search for the saved activity by title. 6. Open a saved item. 7. Unsave one saved item and return to Saved. | H30: Saved trips and activities appear in their corresponding tabs, search returns the expected item, saved content opens correctly, and an unsaved item is removed from the saved list. | I30: OK
A31: F30 | B31: View and edit profile | C31: Secondary function | D31: Done | E31: Verify profile information, social counters and profile editing. | F31: User A is logged in using the account created during F1. 'ATP Planned Trip - [Tester ID]' is Public. | G31: 1. Open the user menu and select My Profile. 2. Verify the username, profile image, trip count and the Followers, Following and Friends values. 3. Verify that public itineraries, including 'ATP Planned Trip - [Tester ID]', are displayed. 4. Record the current profile description. 5. Select Edit profile. 6. Change the description to 'ATP profile test - [Tester ID]'. 7. Save and verify the updated description. 8. Restore the original description if desired. | H31: The profile displays the user's public and social information correctly and editable profile information persists after saving. | I31: OK
A32: F31 | B32: Follow and unfollow users | C32: Secondary function | D32: Done | E32: Verify that following relationships can be created and removed. | F32: User A and User B are the two accounts created during F1. User B is logged in and can find User A through Explore > People. | G32: 1. As User B, open User A's profile. 2. Follow User A. 3. Verify that the button/state changes to Following and the relevant social counter updates. 4. Unfollow User A and verify the relationship is removed. 5. Follow User A again so the relationship remains active for later notification/following checks. 6. Refresh the page. | H32: Follow and unfollow actions update the relationship and counters consistently, and the final Following state persists after refresh. | I32: OK
A33: F32 | B33: Manage users preferences | C33: Secondary function | D33: Done | E33: Verify that the user can change application theme and preferred currency. | F33: User A is logged in using the account created during F1. | G33: 1. Open the user menu and record the current theme. 2. Toggle Dark mode/Light mode. 3. Verify that the interface theme changes. 4. Open My Profile or the currency preference control. 5. Record the current preferred currency. 6. Change the preferred currency to another available currency such as USD or EUR. 7. Verify that the selected currency is shown and monetary values use/display the preference where applicable. 8. Restore the original theme/currency if desired. | H33: The selected theme is applied to the interface and the preferred currency is saved and reflected in relevant monetary displays. | I33: OK
A34: F33 | B34: View notifications | C34: Secondary function | D34: Done | E34: Verify that trip and social events produce accessible notifications. | F34: The previous scenarios were executed with the same User A / User B pair. They generated a trip invitation for User B and social interactions/following events involving User A. | G34: 1. As User B, open Notifications and look for the trip invitation/event generated when joining 'ATP Open Trip - [Tester ID]'. 2. Review the available notification categories/types. 3. As User A, open Notifications. 4. Verify that social events generated by User B, such as follow, like or comment, are represented when the corresponding notification type is supported. 5. Open a notification that provides a navigation target. | H34: Notifications are displayed with the relevant event information and supported notification links navigate to the corresponding trip, user or content context. | I34: OK
A35: F34 | B35: AI-assisted destination suggestions | C35: Secondary function | D35: In progress | E35: Verify the current AI-assisted destination recommendation workflow for an Open Trip. | F35: User A is logged in. An Open Trip that has not yet been finalized exists; create a temporary 'ATP AI Open Trip - [Tester ID]' using F5 if necessary. This feature is still under improvement. | G35: 1. Open the unfinalized Open Trip. 2. Select AI suggestions under Destinations. 3. Complete the preference form using a simple profile such as city break, culture and medium budget. 4. Generate destination suggestions. 5. Review the generated results. 6. Select at least one recommendation to add. 7. Return to the destination proposal list. | H35: The AI workflow completes without a blocking error, returns destination recommendations, and the user can choose which recommendations are added as trip proposals. | I35: N/A | K35: Feature not implemented yet
A36: F35 | B36: AI-assisted activity creation | C36: Secondary function | D36: In progress | E36: Verify the current AI-assisted activity suggestion/creation workflow. | F36: User A is logged in and has a planned trip created during this ATP run with a destination and dates. This feature is still under improvement. | G36: 1. Open a planned trip and select Add activity. 2. Select Create with AI / AI suggestions. 3. Complete the available preference inputs. 4. Generate activity suggestions. 5. Review the suggestions and select one. 6. Verify that the selected suggestion is transferred into the activity creation flow. 7. Adjust required fields if needed. 8. Complete the activity creation. | H36: The AI workflow completes without a blocking error, provides activity suggestions, and a selected suggestion can be used as the basis for a trip activity. | I36: N/A | K36: Feature not implemented yet
A37: F36 | B37: AI-assisted itinerary reorganization | C37: Secondary function | D37: In progress | E37: Verify the current AI-assisted itinerary reorganization workflow. | F37: User A is logged in. A trip created during this ATP run contains at least three activities across the itinerary. This feature is still under improvement. | G37: 1. Open the trip Calendar. 2. Select Reorganise with AI. 3. Start the AI reorganization workflow. 4. Review the proposed activity/date organization. 5. Apply/confirm the proposal if the interface requests confirmation. 6. Verify that all original activities remain in the trip. 7. Reload the calendar and review the resulting dates. | H37: The AI workflow completes without a blocking error, proposes or applies an itinerary organization that can be reviewed by the user, and no trip activities are lost. | I37: N/A | K37: Feature not implemented yet

Sheet Dissonance
A1: Feature ID | B1: Feature Name | C1: Category | D1: Dev status (team) | E1: Objective | F1: Prerequisites | G1: Steps | H1: Expected results | I1: RESULT | J1: Severity | K1: Feedback / anomaly (what you actually saw)
A2: F1 | B2: Install the desktop app | C2: Critical feature | D2: Done | E2: Install Dissonance from the released installer for the tester's OS | F2: A machine matching the Test environment section; installer downloaded from the Releases page | G2: 1. Open the Releases page 2. Download the installer for your OS (.dmg / .exe / .AppImage) 3. Run it (macOS: drag Dissonance to Applications - Linux: chmod +x the AppImage) 4. Launch Dissonance | H2: The app installs and launches to the Upload screen. Any OS security warning can be bypassed with the documented steps. | I2: OK
A3: F2 | B3: Launch the app | C3: Critical feature | D3: Done | E3: The app opens on the Upload screen with no error | F3: App installed | G3: 1. Launch Dissonance 2. Observe the window | H3: A window opens showing the title, the tagline and the drop zone. No error dialog, no blank window. | I3: OK
A4: F3 | B4: Native core loads at startup | C4: Critical feature | D4: Done | E4: Confirm the C++ core (.node addon) is loaded for the current platform and architecture | F4: App installed, any WAV file available | G4: 1. Launch Dissonance 2. Import a WAV file 3. Read the Duration / Sample rate / Channels row on the Analyze screen | H4: Real values are shown (not "-"). No "Core addon not available" message appears. | I4: OK
A5: F4 | B5: Import a file with the file picker | C5: Critical feature | D5: Done | E5: Load a WAV through the native file dialog | F5: App on the Upload screen, atp_stereo_44k.wav on disk | G5: 1. Click the drop zone 2. Select atp_stereo_44k.wav 3. Confirm | H5: The Analyze screen opens showing the file name, its technical info and its waveform. | I5: OK
A6: F5 | B6: Import a file by drag and drop | C6: Critical feature | D6: Done | E6: Load a WAV by dropping it onto the window | F6: App on the Upload screen, a WAV in a file manager window | G6: 1. Drag the WAV out of the file manager 2. Drop it on the drop zone | H6: Same result as picking it: Analyze opens with that file loaded. The OS does not open the file in another application. | I6: OK
A7: F6 | B7: Drop a file anywhere in the window | C7: Secondary function | D7: Done | E7: Dropping outside the drop zone also imports the file | F7: A file already loaded (Analyze screen) | G7: 1. Drag a second WAV over any part of the window 2. Drop it | H7: The new file replaces the current one and Analyze reloads with its info, waveform and tags. | I7: OK
A8: F7 | B8: Cancel the file dialog | C8: Secondary function | D8: Done | E8: Cancelling the picker leaves the app untouched | F8: App on the Upload screen | G8: 1. Click the drop zone 2. Press Cancel in the dialog | H8: The dialog closes, the app stays on Upload, no error is shown. | I8: OK
A9: F8 | B9: Change file from the Analyze screen | C9: Secondary function | D9: Done | E9: Swap the loaded file without restarting the app | F9: A file loaded | G9: 1. Click "Change file" 2. Pick a different WAV (atp_mono_48k.wav) | H9: Analyze reloads with the new file name, new duration / sample rate / channels, new waveform and its own tags. | I9: OK
A10: F9 | B10: Non-WAV audio file | C10: Compatibility | D10: In progress | E10: The app must fail clearly on audio formats the core cannot parse yet | F10: atp_sample.mp3 on disk | G10: 1. Click the drop zone 2. Select atp_sample.mp3 (the picker allows mp3/ogg/m4a/flac) 3. Observe the Analyze screen 4. Click Process | H10: The app does not crash: either the file is refused with a readable message, or processing fails with a readable message and returns to Analyze. Only WAV is supported today. | I10: OK
A11: F10 | B11: Corrupt or truncated WAV | C11: Critical feature | D11: Done | E11: Malformed input must not crash the app | F11: atp_corrupt.wav on disk | G11: 1. Import atp_corrupt.wav 2. Click Process | H11: An error message is shown and the app stays usable. No crash, no freeze, no silent success producing a broken file. | I11: OK
A12: F11 | B12: Display WAV technical info | C12: Critical feature | D12: Done | E12: Show duration, sample rate and channel count of the imported file | F12: atp_stereo_44k.wav imported | G12: 1. Import the file 2. Read the info row 3. Compare with the file's real properties (OS file info or a DAW) | H12: Duration is shown as m:ss, sample rate in Hz and channel count, all matching the real file. | I12: OK
A13: F12 | B13: Waveform rendering | C13: User interface | D13: Done | E13: Draw the waveform of the imported file | F13: A WAV imported | G13: 1. Look at the waveform panel on the Analyze screen | H13: The waveform is drawn across the full panel width, visibly matches the audio, and the transport controls are visible. | I13: OK
... A27: F26 | B27: Modes and slider are mutually exclusive | C27: User interface | D27: Done | E27: The two protection controls cannot both be active | F27: Analyze screen with a file loaded | G27: 1. Tick any processing mode 2. Try to move the strength slider 3. Untick every mode | H27: With at least one mode ticked the slider is disabled and the helper text says so. Unticking every mode re-enables the slider. | I27: OK
A28: F27 | B28: Protection strength at 0% | C28: Critical feature | D28: In progress | E28: Check what the app actually does when protection is set to zero | F28: A WAV imported, no processing mode ticked | G28: 1. Set the strength slider to 0% 2. Leave every mode unticked 3. Click Process 4. A/B listen on the Compare screen and compare the two waveforms | H28: Processing completes without error. A 0% setting should mean an untouched pass-through; in this build the app sends no options at 0%, so the core falls back to its own defaults (white noise at strength 0.5) and the output is audibly and visibly modified. Mark non-compliant if you hear or see a difference. | I28: N/A | K28: Feature not implemented yet
A29: F28 | B29: Process a file | C29: Critical feature | D29: Done | E29: Run the core pipeline on the imported WAV | F29: A WAV imported, a strength or a set of modes chosen | G29: 1. Click Process 2. Wait for the run to finish | H29: A loading screen with a spinner and progress bar appears, then the Compare screen opens with the original and the processed file both loaded. | I29: OK
A30: F29 | B30: Header shown only on the Upload screen | C30: User interface | D30: Done | E30: The intro header makes way for the working screens | F30: App running | G30: 1. Look at the header on Upload 2. Import a file 3. Process it 4. Click Restart | H30: Title and tagline show on Upload, are hidden on Analyze, Processing and Compare, and reappear after Restart. | I30: OK
A31: F30 | B31: Processing failure is reported | C31: Critical feature | D31: In progress | E31: A failed run returns the tester to Analyze with a readable message | F31: atp_corrupt.wav imported | G31: 1. Click Process 2. Wait | H31: The app returns to the Analyze screen without crashing, but there is no visible error [KNOWN DEFECT]. The failure message ("Failed to read audio data") only reaches the main-process terminal, so it appears when the app is launched from a terminal, but once the app is packaged it is not visible anywhere. There is no error component in the interface (no toast, banner or snackbar), so the tester sees a silent return to Analyze with no indication the file was corrupt. | I31: N/A | K31: Feature not implemented yet
A32: F31 | B32: Restart during processing | C32: Secondary function | D32: Done | E32: The Restart button abandons an in-flight run cleanly | F32: atp_fulltrack.wav imported (long enough to catch the loading screen) | G32: 1. Click Process 2. While the spinner is showing, click the Restart button (top right) 3. Wait 30 seconds | H32: The app returns to the Upload screen immediately and the late result is discarded - the Compare screen never appears afterwards. | I32: OK
A33: F32 | B33: Processing time on a real track | C33: Secondary function | D33: Done | E33: Check that processing a full-length track stays workable | F33: atp_fulltrack.wav (3–4 min, 44.1 kHz stereo) | G33: 1. Import the track 2. Set the strength to 50% 3. Click Process and time the run 4. Try moving the window while it runs | H33: Processing finishes and the window stays responsive throughout (no beachball / "not responding"). Note the measured time in Feedback. | I33: OK
A34: F33 | B34: Original vs processed technical info | C34: Critical feature | D34: Done | E34: The processed file must keep the original audio format | F34: A run completed (Compare screen) | G34: 1. Read the Original info panel 2. Read the Processed info panel 3. Compare them field by field | H34: Duration, sample rate and channel count are identical on both sides; only the file name differs. Note: the app does not display bit depth, and the core always writes 16-bit PCM output. | I34: OK
A35: F34 | B35: Two independent waveform players | C35: Critical feature | D35: Done | E35: A/B listen to the original and the processed file | F35: Compare screen | G35: 1. Play the original 2. Play the processed file 3. Seek in each of them | H35: Both players work independently, each shows its own waveform, and seeking in one does not affect the other. | I35: OK
A36: F35 | B36: The perturbation is inaudible | C36: Critical feature | D36: In progress | E36: The protection must not be audible on a normal listen; this is the core product claim. This ATP cycle tests the released core build (the pre mask-aware engine): it injects flat white noise behind an 8 kHz high-pass plus a fixed 0.8 gain, so this run re-baselines what that build actually sounds like on the three reference tracks and the tester's own library. | F36: atp_fulltrack.wav, atp_track_c.wav and atp_track_d.wav each processed at 50% strength; headphones; the Compare screen is used for A/B switching | G36: 1. Process atp_fulltrack.wav at 50% and A/B the same passage, switching back and forth on the Compare screen 2. Repeat on atp_track_c.wav (quiet and sparse, least masking headroom) 3. Repeat on atp_track_d.wav (loud dense master) 4. Repeat one of them at 100% strength (further modes stack as strength rises) 5. Finally, repeat on two or three tracks from the tester's own music library | H36: Expected at 50% strength on this pre mask-aware core: no added hiss, artefact or distortion beyond the known character of this build. Watch atp_track_c.wav in particular - the quiet-and-sparse case has the least masking headroom and is the one most likely to reveal the flat noise; a faint added breath/hiss on that track is expected and should be noted, not treated as corruption. At 100% strength the additional modes stack (phase distortion, then spectral gate, then pink noise), so expect a more coloured result and say in Feedback whether you can still pick the processed file reliably. Every case comes out slightly quieter: this build applies a fixed 0.8 linear gain (about -1.9 dB) that the UI cannot change, so a level difference alone is not an artefact. No loudness normalisation or limiter is in this build yet, so on atp_track_d.wav compare at a matched, comfortable level. Say which track you heard anything on, and at which strength. | I36: N/A | K36: Feature not implemented yet
A37: F36 | B37: Waveforms are visibly comparable | C37: User interface | D37: Done | E37: The processed waveform should track the original | F37: Compare screen | G37: 1. Compare the two waveform shapes side by side | H37: The processed waveform has the same overall shape as the original but a visibly lower amplitude (≈80% of it) - that is the fixed gain stage, not a fault. No clipping, no silence, no change in shape or length. | I37: OK
A38: F37 | B38: Edited tags carried into the output | C38: Secondary function | D38: Done | E38: Metadata entered before processing ends up in the processed file | F38: Tags edited on the Analyze screen before processing | G38: 1. Edit Title and Artist 2. Process 3. Export the result 4. Import the exported file back into Dissonance | H38: The exported file carries the edited Title and Artist. | I38: OK
A39: F38 | B39: Export the processed file | C39: Critical feature | D39: Done | E39: Save the protected file to a chosen location | F39: Compare screen | G39: 1. Click Export 2. Choose a destination folder and file name 3. Confirm | H39: The file is written to the chosen location and the app returns to the Upload screen, ready for the next file. | I39: OK
A40: F39 | B40: Cancel the export | C40: Secondary function | D40: Done | E40: Cancelling the save dialog keeps the result available | F40: Compare screen | G40: 1. Click Export 2. Cancel the save dialog | H40: No file is written, the app stays on Compare and Export can be clicked again. | I40: OK
A41: F40 | B41: Exported file plays in other software | C41: Compatibility | D41: Done | E41: The output must be a valid WAV for the rest of the world | F41: A file exported | G41: 1. Open the exported file in a media player or a DAW 2. Play it from start to end 3. Check its properties | H41: The file opens and plays normally at full length, with the same duration, sample rate and channel count as the original. | I41: OK
A42: F41 | B42: The original file is never overwritten | C42: Critical feature | D42: Done | E42: Processing must not touch the tester's source file | F42: A copy of the original WAV kept aside | G42: 1. Note the original's size and modification date 2. Import, process and export it 3. Re-check the original and play it | H42: The original audio is unchanged and still plays. Only its tags change, and only if the tester edited them. The processed audio is written to the export destination only. | I42: OK
A43: F42 | B43: Temporary files are cleaned up | C43: Secondary function | D43: Done | E43: The app must not leave processed audio behind on disk | F43: A run completed and exported | G43: 1. Process and export a file 2. Quit the app 3. Look for a "dissonance" folder in the system temp directory | H43: Temporary processed files are removed after export and at quit - the folder is empty or absent. | I43: OK
A44: F43 | B44: Restart button | C44: Secondary function | D44: Done | E44: Return to the start of the flow from any screen | F44: A file imported | G44: 1. Click the Restart button (top right) from the Analyze screen 2. Import and process a file, then click Restart from the Compare screen | H44: In both cases the app returns to the Upload screen with the previous file, result and metadata cleared. | I44: OK
A45: F44 | B45: Light and dark theme follow the OS | C45: User interface | D45: Done | E45: The app matches the system appearance | F45: App running | G45: 1. Switch the OS between light and dark mode on each screen (Upload, Analyze, Compare) | H45: The interface switches theme without restarting the app, and every label, field and button stays readable in both themes. | I45: OK
A46: F45 | B46: Window resizing | C46: User interface | D46: Done | E46: The layout survives resizing | F46: A file imported | G46: 1. Resize the window from small to full screen on the Analyze screen 2. Do the same on the Compare screen | H46: Panels reflow (two columns become one at narrow widths), nothing overlaps or is clipped, and every control stays reachable. | I46: OK
A47: F46 | B47: Quit and relaunch | C47: Secondary function | D47: Done | E47: Clean shutdown and restart | F47: App running with a file loaded | G47: 1. Quit the app 2. Relaunch it | H47: The app exits without hanging and reopens on the Upload screen with no leftover state from the previous session. | I47: OK
A48: F47 | B48: Second launch and multiple windows | C48: Secondary function | D48: In progress | E48: Establish how the app behaves when it is launched twice | F48: App already running with a file imported | G48: 1. Launch Dissonance a second time while the first window is open 2. Import the SAME WAV in both windows 3. Edit a different tag in each window and let both save 4. Re-import the file | H48: This build has no single-instance lock, so a second window is expected to open. Both windows must stay usable, and the tag writes from the two windows must not corrupt the file: it still plays and holds one coherent set of tags. Mark non-compliant on any crash, unplayable file, or lost audio. | I48: N/A | K48: Feature not implemented yet
A49: F48 | B49: 24-bit WAV input (both header types) | C49: Compatibility | D49: In progress | E49: Check the app handles 24-bit WAVs, in both header forms a real export produces | F49: atp_24bit.wav and atp_24bit_ext.wav on disk; a DAW or audio tool that reports bit depth | G49: 1. Import atp_24bit.wav (plain PCM header) 2. Read the Duration / Sample rate / Channels row and the Metadata panel 3. Process, export, and check the exported file's bit depth in a DAW 4. Now import atp_24bit_ext.wav (WAVE_FORMAT_EXTENSIBLE header) 5. Read the same fields again | H49: Both files should import and process. atp_24bit.wav is expected to work: the exported file is valid and plays, but is written as 16-bit PCM - record the bit-depth reduction in Feedback. KNOWN DEFECT on atp_24bit_ext.wav: the parser accepts only audioFormat 1 (PCM) and 3 (float) and rejects 65534, so the info row and every metadata field show "-" with no error message shown to the user. Confirm you see that, then report what happens when you click Process. Most 24-bit DAW exports use this header, so this affects real files. | I49: N/A | K49: Feature not implemented yet
A50: F49 | B50: Run a protection check on a processed file | C50: Critical feature | D50: In progress | E50: Measure, inside the app, whether the protection actually worked on this track | F50: NOT TESTABLE THIS CYCLE - the verification engine is not in the app yet. A file processed and sitting on the Compare screen | G50: 1. Process a track 2. On Compare, start the protection check 3. Wait for it to finish | H50: The check runs on the original/processed pair without leaving the app, shows progress while it works, and ends on a report screen. The app stays responsive throughout. | I50: N/A | K50: Feature not testable
A51: F50 | B51: Human audibility score (SNR) | C51: Critical feature | D51: In progress | E51: Report how audible the perturbation is to a human listener | F51: NOT TESTABLE THIS CYCLE - the verification engine is not in the app yet. A protection check completed | G51: 1. Read the SNR figure in the report 2. Re-run at a low and a high protection strength and compare | H51: SNR is reported in dB against the published thresholds: ≥ 30 dB imperceptible, 20–30 dB borderline, < 20 dB clearly audible. Higher protection strength lowers the SNR. | I51: N/A | K51: Feature not testable
A52: F51 | B52: Lyrics confusion (speech transcription) | C52: Secondary function | D52: In progress | E52: Report whether a transcription model reads different words off the protected file | F52: NOT TESTABLE THIS CYCLE - the verification engine is not in the app yet. A protection check completed on a track with vocals | G52: 1. Read the lyrics section of the report 2. Compare the original and perturbed transcriptions shown side by side | H52: Both transcriptions are shown with a confusion score in %. ≥ 50% word divergence counts as success. A track with no vocals is reported as not applicable rather than as a failure. | I52: N/A | K52: Feature not testable
A53: F52 | B53: Genre and encoder confusion | C53: Secondary function | D53: In progress | E53: Report whether music-understanding models see a different track after protection | F53: NOT TESTABLE THIS CYCLE - the verification engine is not in the app yet. A protection check completed | G53: 1. Read the genre label before and after 2. Read the encoder confusion score | H53: The top genre label is shown for both files with whether it changed, plus an encoder confusion score in %. ≥ 30% counts as success. | I53: N/A | K53: Feature not testable
A54: F53 | B54: Overall verdict | C54: Critical feature | D54: In progress | E54: Give a single, readable answer to "is this track protected?" | F54: NOT TESTABLE THIS CYCLE - the verification engine is not in the app yet. A protection check completed | G54: 1. Read the summary at the top of the report 2. Run the check again on an unprocessed file (same file twice) | H54: The report leads with a pass/fail verdict and a count of metrics passed. Protection only passes when it is inaudible AND confuses the models. The same file twice yields no confusion and an explicit fail. | I54: N/A | K54: Feature not testable
A55: F54 | B55: Export the verification report | C55: Secondary function | D55: In progress | E55: Keep the evidence outside the app | F55: NOT TESTABLE THIS CYCLE - the verification engine is not in the app yet. A protection check completed | G55: 1. Export the report 2. Open the exported file | H55: The report is written to a chosen location in a readable, machine-parsable form, carrying the file names, the scores, the thresholds used and the model versions. | I55: N/A | K55: Feature not testable
A56: F55 | B56: First run: model download and offline behaviour | C56: Compatibility | D56: In progress | E56: Establish what the check needs from the network, and what happens without it | F56: NOT TESTABLE THIS CYCLE - the verification engine is not in the app yet. A machine that has never run the check | G56: 1. Start a protection check on a fresh install and watch for any download 2. Repeat with the machine offline 3. Re-run once the models are cached | H56: The app states up front what it needs to download and how large it is (the reference models total roughly 3.3 GB) and asks before doing it. Offline, the check fails with a clear explanation instead of hanging, and protection and export keep working. Later runs use the cache and need no network. NOTE: this is the only part of Dissonance that would touch the network - the privacy claim on the Info tab must be reworded if it ships. | I56: N/A | K56: Feature not testable
A57: F56 | B57: Hardware limits and graceful degradation | C57: Compatibility | D57: In progress | E57: The check must not break the app on machines that cannot run the models | F57: NOT TESTABLE THIS CYCLE - the verification engine is not in the app yet. A low-RAM machine, and a non-Apple-Silicon machine | G57: 1. Start a protection check on each machine 2. Watch memory use and the app's responsiveness | H57: On a machine that cannot run the models the app says so plainly and stays usable - protection and export still work. It does not freeze, exhaust memory or crash. Record the machine and the outcome in Feedback. | I57: N/A | K57: Feature not testable

Sheet Horus
A1: Feature ID | B1: Feature Name | C1: Category | D1: Dev status (team) | E1: Objective | F1: Prerequisites | G1: Steps | H1: Expected results | I1: RESULT | J1: Severity | K1: Feedback / anomaly (what you actually saw)
A2: F1 | B2: Install and start Horus from the archive | C2: Critical feature | D2: Done | E2: A tester installs Horus by extracting the archive and double-clicking one file, with no terminal, no clone and no manual editing, and ends up on the login screen | F2: Docker Desktop installed AND RUNNING; Python 3.11+; free disk of 150 GB for a CPU install or 125 GB for GPU; Horus-Beta-0.1.0.zip downloaded from the OneDrive link on the Info & Access tab. The disk figures are measured build PEAKS. The install settles to about 130 GB (CPU) or 110 GB (GPU) afterwards. Download is about 25 GB. No NVIDIA GPU is required: the installer detects the hardware and selects a CPU profile itself. | G2: 1. Extract the WHOLE archive to a folder 2. Read README-FIRST.txt (40 lines, plain text) 3. Run the launcher for your platform: Windows double-click START-HERE-Windows.bat; macOS right-click START-HERE-macOS.command and choose Open; Linux ./START-HERE-Linux.sh 4. Choose a file-access option when asked (option 1 uses the bundled sample documents), then confirm 5. Wait. The first run builds the images, then downloads the model weights. Allow 1.5-2 hours. The installer prints progress and is not frozen. Later starts take about 90 s. 6. When it reports success, open http://localhost:3000 in a browser | H2: The installer runs its preflight checks (Python, Docker, Compose, free disk, network, ports), probes the hardware, chooses a profile, builds and starts the stack, and finishes with a 9-step smoke test. On failure it gives a distinct exit code and an actionable message, plus install-log.txt and horus-profile.json to send back. http://localhost:3000 shows the Horus login screen. With an NVIDIA GPU: 12 services are Up, 5 of them health-checked and healthy (mas, postgres, redis, rabbitmq, vllm). Without a GPU: the installer prints a warning up front, selects the CPU profile, and 11 services are Up with 4 healthy. The install still completes and reports success. Only F18, F19 and F20 are out of reach on a CPU install; record those as NOT APPLICABLE. vllm downloads its model last, so it is the last to go healthy. Allow extra time. | I2: OK
A3: F2 | B3: Open Horus as a desktop application | C3: User interface | D3: In progress | E3: After installing, the tester opens an application window rather than being told to visit localhost:3000, and the application manages the stack for them | F3: F1 passed | G3: 1. Open the app: Windows app/Horus.exe / macOS app/Horus.app / Linux install app/Horus_0.1.0_amd64.deb then launch Horus 2. Accept the unsigned-binary warning (Windows: More info then Run anyway; macOS: right-click then Open, twice) 3. Watch the status screen while the stack starts 4. Use the Horus menu: Stop, Restart, Open install-log.txt, Open horus-profile.json 5. Close the window and answer the shutdown prompt | H3: A native window titled Horus opens, with the Horus icon and no browser chrome. A status screen shows: the current step one row per service with its health elapsed time the raw Docker output on demand When the stack is ready the window is replaced by the Horus client loaded from http://localhost:3000, so the session token is preserved. Reachable from both the native menu and the status window: Stop, Restart, Open install-log.txt, Open horus-profile.json Closing asks whether to leave the stack running, and remembers the answer. localhost:3000 in a browser remains a supported fallback. | I3: OK
A4: F3 | B4: Sign in with the seeded administrator | C4: Critical feature | D4: Done | E4: Sign in with the administrator account that MAS creates automatically at startup. The tester does not create it. | F4: F1 passed | G4: 1. Go to http://localhost:3000/auth/login 2. Username: admin 3. Password: admin 4. Submit | H4: Login succeeds and the dashboard loads with the Admin section visible. This account already exists: MAS seeds it at startup. Registering a new account never grants admin, whatever the creation order. | I4: OK
A5: F4 | B5: Manage users as an admin (view, create, change role, delete) | C5: Critical feature | D5: Done | E5: An admin sees every account, creates the team accounts, changes a role and sees it take effect at once, and removes an account so that it really loses access | F5: Signed in as the seeded administrator (F3) | G5: 1. Go to /admin/users. The table lists every account with its role; the search field and the role filter narrow it. 2. Click Create New User. Username horus.admin, password HorusATP2026!, role admin. Submit. 3. Repeat for horus.manager (manager), horus.user (user) and horus.user2 (user). 4. Click Edit User Role on horus.user2, select manager, save. 5. In a private window, log in as horus.user2 and open /tasks. 6. Back as admin, set horus.user2 to user again; in the private window, reload /tasks. 7. Create horus.disposable / HorusATP2026! with the user role, and log in as it in a second private window; leave that window open. 8. Back as admin, click Delete User on horus.disposable and confirm in the dialog. Reload the page. 9. Try to log in as horus.disposable again. In the window from step 7, reload /dashboard. | H5: Steps 1-3: every account is listed with its username and role. New accounts appear immediately with the role chosen, and each can log in. Steps 4-6: as manager, horus.user2 can view the task queue; back as user, the manager-only actions are no longer available. No restart is needed. Steps 8-9: a confirmation dialog is shown first, then horus.disposable disappears from the table. Login is refused, and the still-open session can no longer load protected data. | I5: OK
A6: F5 | B6: Register a standard account | C6: Critical feature | D6: Done | E6: A newcomer can self-register, receives the default user role, and the password policy holds | F6: F1 passed | G6: 1. Go to /auth/register 2. First try the password horus (too short, no digit or symbol) 3. Then register horus.user / HorusATP2026! 4. Log in | H6: The weak password is refused with a readable message: at least 10 characters with an uppercase, a lowercase, a digit and a special character. The same rule applies on the sign-up form, in the Admin > Users panel and on the MAS server, which returns a 422 the web client displays. The valid registration creates an account with the user role, and the Admin section is NOT visible for it. | I6: OK
A7: F6 | B7: Log in | C7: Critical feature | D7: Done | E7: Sign in with an existing account and reach the dashboard | F7: An existing account | G7: 1. Go to /auth/login 2. Enter username and password 3. Submit | H7: Login succeeds within 2 s and the user lands on the dashboard. | I7: OK
A8: F7 | B8: Log out | C8: Secondary function | D8: Done | E8: End the session and invalidate the token | F8: Stack running, tester logged in to the web client | G8: 1. Click the account menu 2. Click Log out 3. Try to navigate back to /dashboard using the browser back button | H8: The user returns to the login page and the back button does not restore an authenticated view. | I8: OK
A9: F8 | B9: Register an agent | C9: Critical feature | D9: Done | E9: An admin can add a specialised agent and receive its API key | F9: Logged in as horus.admin | G9: 1. Go to /admin/agents 2. Click Register New Agent 3. Name: FinCorp-Analyst 4. Description: Financial analyst agent 5. Skills: financial_analysis, compliance, reporting, document_qa 6. Submit 7. Copy the generated API key | H9: The agent is created, an API key is returned exactly once and is displayed to the admin, and the agent appears in the registry. | I9: OK
A10: F9 | B10: View the agent registry | C10: Critical feature | D10: Done | E10: Any authenticated user can see which agents exist and whether they are up | F10: F8 passed | G10: 1. Go to /dashboard 2. Read the agents list 3. Repeat while logged in as horus.user | H10: FinCorp-Analyst is listed with its skills and an online status, for the admin and for the standard user alike. | I10: OK
A11: F10 | B11: View agent details | C11: User interface | D11: Done | E11: See one agent's full record from the admin agents page | F11: F8 passed; signed in as horus.admin | G11: 1. Go to http://localhost:3000/admin/agents 2. Click FinCorp-Analyst in the list to open its details 3. Compare what is shown with the agent card on /dashboard | H11: The detail view shows the agent's id, name, description, skills and current status, and it matches what the dashboard shows for the same agent. | I11: OK
A12: F11 | B12: Unregister an agent | C12: Critical feature | D12: Done | E12: An admin can remove an agent from the registry | F12: F8 passed, logged in as horus.admin | G12: 1. Go to /admin/agents 2. Unregister FinCorp-Analyst 3. Confirm 4. Reload /dashboard 5. Register FinCorp-Analyst again, so later scenarios still have it | H12: The agent disappears from the registry and no new task is routed to it. After step 5 it is back and routable. | I12: OK
A13: F12 | B13: Upload documents | C13: Critical feature | D13: Done | E13: Load the company documents into the knowledge store and see them analysed automatically | F13: 1. F1 passed, stack running 2. Tester logged in to the web client 3. The 5 corpus documents to hand: horus/demo_assets/ inside the extracted archive. No repository access is needed - they ship in the ZIP. Accepted file types: PDF, Markdown (.md), Excel (.xlsx), plain text and configuration files (for example .env), and images (.jpeg, .png). Most common formats are accepted. The five sample files are .md. | G13: 1. Go to /knowledge-store 2. Click Upload Files 3. Select all 5 .md files from horus/demo_assets/ in the folder you extracted 4. Confirm the upload 5. Wait for processing to finish 6. Click each document to open its detail panel | H13: All 5 documents are ingested, each in under 20 s. The document list shows every one of them with its category, and the Documents Stored and Storage Used tiles match the number uploaded. Without any manual tagging, each document's detail panel shows an auto-detected category (Finance, HR, Compliance, IT), a short summary, and extracted entities: people, amounts and dates. The expected category and entities per file are listed on the Info & Access tab under Test corpus. | I13: OK
A14: F13 | B14: Search the documents | C14: Critical feature | D14: Done | E14: Find relevant excerpts by typing a query, then narrow them by category | F14: F12 passed | G14: 1. On /knowledge-store, type Q4 revenue in the search field 2. Apply the category filter Finance | H14: Results come back in under 3 s, ranked, with a readable text excerpt per hit. The category filter removes non-Finance documents. | I14: KO | J14: Major | K14: No result come back
A15: F14 | B15: List categories | C15: Secondary function | D15: Done | E15: See the categories the pipeline assigned on its own, as offered in the knowledge store's filter | F15: F12 passed | G15: 1. On /knowledge-store, open the category filter 2. Compare the list it offers with the category shown on each document in the list | H15: The filter offers exactly the categories that were assigned to the uploaded documents, with no duplicates and no empty entries. | I15: KO | J15: Major | K15: No catecory filter
A16: F15 | B16: Delete a document | C16: Critical feature | D16: Done | E16: A user can remove a document, and the removal reaches search and chat, not only the list | F16: F12 passed | G16: 1. Go to /knowledge-store 2. Delete 5_IT_Security_Policy.md 3. Confirm 4. Reload the page 5. Search the corpus for a phrase that only existed in that document 6. Ask the same thing in a chat conversation | H16: Steps 1-4: the document leaves the list and the Total Documents counter drops by one. Steps 5-6: no excerpt from the deleted document is returned and the agent no longer cites it. No phantom results. | I16: OK
A17: F16 | B17: Create a conversation | C17: Critical feature | D17: Done | E17: A user can open a new named conversation | F17: Stack running, tester logged in to the web client | G17: 1. Go to /conversations 2. Click New conversation 3. Name it ATP-Test-01 4. Confirm | H17: The conversation is created and appears at the top of the list straight away. | I17: OK
A18: F17 | B18: Send a message | C18: Critical feature | D18: Done | E18: A user can post a message inside a conversation | F18: F16 passed; at least one agent registered (F8) | G18: 1. Open the conversation 2. Type: What was our Q4 2025 revenue? 3. Press Enter | H18: The message appears in the thread in under 1 s and is attributed to the sender. | I18: OK
A19: F18 | B19: Ask a question and receive a grounded answer | C19: Critical feature | D19: Done | E19: Ask one factual question and wait for an answer drawn from the uploaded documents, with its source named | F19: GPU REQUIRED. On a CPU-only machine the answer does arrive - about 1-2 min on a 12-core machine, up to about 7 min on 4 cores - but digits are corrupted in the output, so the accuracy target cannot be met. A CPU tester records this as NOT APPLICABLE, not failed. F12 passed (corpus uploaded); an agent is online | G19: 1. In a conversation, ask: What was our Q4 2025 revenue? 2. Wait for the answer | H19: GPU REQUIRED - see Prerequisites. The answer arrives in under 15 s, identifies Q4 2025 revenue as $4.2M, and cites 1_Q4_2025_Financial_Report.md as its source. The figure may be returned on its own (for example '$4.2M'). That is acceptable as long as the source is named, either in the message or in the sources panel beside it. Answers are cached by exact question text, so a re-test needs different wording. | I19: OK
A20: F19 | B20: Ask a complex question spanning several documents | C20: Critical feature | D20: Done | E20: Ask one question that needs two documents and wait for an answer that uses both | F20: GPU REQUIRED. On a CPU-only machine the answer does arrive - about 1-2 min on a 12-core machine, up to about 7 min on 4 cores - but digits are corrupted in the output, so the accuracy target cannot be met. A CPU tester records this as NOT APPLICABLE, not failed. F12 passed; an agent is online | G20: 1. Ask: Compare our Q4 spend against what the expense policy allows and flag anything out of policy. 2. Wait for the answer | H20: GPU REQUIRED - see Prerequisites. The answer arrives in under 60 s and cites BOTH 1_Q4_2025_Financial_Report.md and 4_Expense_Policy.md. It must show, in the answer text: the Q4 spend figures it used the matching threshold from the expense policy a stated conclusion on whether each item is within policy A bare yes or no, or an answer citing only one document, does not pass. | I20: KO | J20: Major | K20: Bad reponse
A21: F20 | B21: Ask a question outside the corpus | C21: Critical feature | D21: In progress | E21: The agent must not invent an answer it cannot ground | F21: GPU REQUIRED. On a CPU-only machine the answer does arrive - about 1-2 min on a 12-core machine, up to about 7 min on 4 cores - but digits are corrupted in the output, so the accuracy target cannot be met. A CPU tester records this as NOT APPLICABLE, not failed. F12 passed; an agent is online | G21: 1. Ask a question with no answer in the corpus, e.g. What is the capital of Peru? | H21: GPU REQUIRED - see Prerequisites. The agent states that the knowledge base contains nothing relevant instead of presenting an ungrounded answer as fact. | I21: OK
A22: F21 | B22: View message history | C22: Critical feature | D22: Done | E22: A conversation reopens with its full history in the right order | F22: F17 passed; the conversation contains at least two messages | G22: 1. Leave the conversation 2. Reload the page 3. Reopen the same conversation | H22: Every message is restored in chronological order with the correct author. | I22: OK
A23: F22 | B23: List conversations | C23: Critical feature | D23: Done | E23: A user sees all of their own conversations | F23: F16 passed (ATP-Test-01 exists) | G23: 1. Go to /conversations 2. Create two more conversations, named ATP-Test-02 and General-Test 3. Reload the page | H23: All three conversations (ATP-Test-01, ATP-Test-02, General-Test) are listed with their names, and the list survives a reload. | I23: OK
A24: F23 | B24: Search conversations | C24: User interface | D24: Done | E24: Find a conversation by name in a long list | F24: F22 passed with several conversations | G24: 1. On /conversations, type ATP in the search field | H24: Only conversations whose name matches are shown; clearing the field restores the full list. | I24: OK
A25: F24 | B25: Delete a conversation | C25: Critical feature | D25: Done | E25: A user can remove a conversation they own; an admin or manager can remove any | F25: F16 passed; horus.user, horus.admin and horus.manager accounts exist | G25: 1. As horus.user on /conversations, delete ATP-Test-01 2. Confirm 3. Reload the page 4. Still as horus.user, create a conversation named ATP-Moderation 5. Log in as horus.admin and delete ATP-Moderation 6. As horus.user, create ATP-Moderation-2; log in as horus.manager and delete it | H25: Steps 1-3: the conversation disappears from the list and its messages are gone with it. Steps 4-6: both the admin and the manager can delete a conversation they do not own, and the owner no longer sees it. | I25: OK
A26: F25 | B26: Create a task | C26: Critical feature | D26: Done | E26: A user can submit work with a demand and required skills | F26: An agent is registered (F8); logged in | G26: 1. Go to /tasks/new 2. Demand: Summarise the Q4 financial report 3. Required skills: financial_analysis, document_qa 4. Submit | H26: The task is accepted, given an id, and appears with status pending then running. | I26: KO | J26: Blocking | K26: Crash and "something went wrong"
A27: F26 | B27: Route a task to a matching agent | C27: Critical feature | D27: Done | E27: Tasks reach an agent whose skills actually match | F27: F25 passed; at least two agents with different skills registered | G27: 1. Register a second agent with unrelated skills 2. Create a task requiring financial_analysis 3. Follow the task to completion 4. Check the RabbitMQ UI at http://localhost:15672 | H27: The task is routed to FinCorp-Analyst and not to the unrelated agent; the queue shows the message on the matching route. | I27: OK
A28: F27 | B28: Receive a task result without refreshing | C28: Critical feature | D28: Done | E28: The result is pushed to the user without a manual refresh | F28: F25 passed; the conversation view is open | G28: 1. Submit a task 2. Leave the page open without refreshing 3. Wait for the agent to finish | H28: A task-result notification arrives over the WebSocket and the UI updates on its own; the payload matches the detail page. | I28: OK
A29: F28 | B29: View the task list | C29: Critical feature | D29: Done | E29: Browse the submitted tasks and see the state of the queue on the same page | F29: F25 passed; several tasks submitted, at least one completed and one cancelled (F31) | G29: 1. Go to /tasks 2. Read the Recent tasks table 3. Read the tiles above it: Pending, Running, Completed, Failed, Cancelled and Timeout, plus Total Tasks and Success Rate | H29: The submitted tasks are listed with their status. The six state tiles and the two totals add up: Total Tasks equals the number of tasks listed, and each tile matches the count of tasks in that state in the table. | I29: KO | J29: Major | K29: The tiles and the table not add up. total tasks ashowed 10 while the recent task table listed 8
A30: F29 | B30: Open a task's detail view | C30: User interface | D30: Done | E30: Inspect one task's full record | F30: F25 passed | G30: 1. On /tasks, click a task 2. Read its detail page | H30: The page shows the demand, required skills, assigned agent, status, timestamps and the result when the task has finished. | I30: Partial | K30: Skils are not there and the created /finished tiemestamps
A31: F30 | B31: Cancel a task | C31: Critical feature | D31: Done | E31: An admin can stop a task that is pending or already running, from the task's own page | F31: F25 passed; signed in as horus.admin | G31: 1. On /tasks, submit a new task 2. While it is still pending or running, click it to open its page at /tasks/<task id> 3. Click Cancel and confirm 4. Go back to /tasks | H31: The task moves to Cancelled within 5 s, the Cancelled counter on /tasks increases by one, and no result is produced for it afterwards. | I31: OK
A32: F31 | B32: Access the dashboard | C32: Critical feature | D32: Done | E32: The landing view after login loads quickly and its analytics update live | F32: Signed in; at least one agent registered (F8) | G32: 1. Log in and land on /dashboard 2. Reload five times and note the load time each time 3. Watch the analytics graph for about 60 s 4. In a second tab, submit a task, and keep watching the graph | H32: The dashboard renders in under 3 s on each of the five reloads, with the agents list and the analytics widget, and no error state. The graph refreshes about every 10 s, and the active agents, running tasks and pending tasks series move when the new task is submitted. | I32: OK
A33: F32 | B33: Navigate with the command palette | C33: User interface | D33: Done | E33: Reach the main sections from the keyboard | F33: Stack running, tester logged in to the web client | G33: 1. Open the command palette from the navigation bar 2. Choose Go to Dashboard, then Open Chat, then Knowledge Store | H33: Each entry navigates to the matching page without a full page reload. | I33: OK
A34: F33 | B34: Open the logs page | C34: Secondary function | D34: Done | E34: Centralised logs are readable inside the product, without Grafana | F34: Logged in as horus.admin; traffic generated by earlier scenarios | G34: 1. Go to /admin/logs 2. Filter by service (mas, agent, knowledge-store) | H34: Recent log lines from the selected service are shown and reflect the actions performed during this test run. | I34: OK
A35: F34 | B35: Open the metrics page | C35: Secondary function | D35: Done | E35: Service metrics are readable inside the product | F35: Logged in as horus.admin | G35: 1. Go to /admin/metrics 2. Read the request-rate and latency panels 3. Cross-check with http://localhost:8000/metrics | H35: Metrics are displayed for the running services and are consistent with the raw Prometheus endpoint. | I35: OK
A36: F35 | B36: Open the traces page and follow a request | C36: Secondary function | D36: Done | E36: A request can be followed end to end across services | F36: Logged in as horus.admin; at least one chat exchange completed | G36: 1. Go to /admin/traces 2. Open a trace for a chat request 3. Expand the spans | H36: The trace shows the hops across MAS, RabbitMQ, the agent and the knowledge store, with per-span timings. | I36: Partial | J36: Major | K36: /admin/traces and opens them with a span waterfall and per-span things
A37: F36 | B37: Run the web client in different browsers | C37: Compatibility | D37: In progress | E37: The web client behaves the same across the main browsers | F37: Stack running | G37: 1. Run F6, F17, F12 and F31 in Chrome 2. Repeat in Firefox 3. Repeat in a third browser for your platform: Windows Edge macOS Safari Linux Chromium (Edge is not required) | H37: Login, chat, upload and dashboard behave identically in all three browsers tested, with no console errors and no broken layout. Record which third browser you used. | I37: Partial | J37: Minor | K37: tested chrome 131 and firefox 133: login chat message wieh answer document upload and dashboard all bahave the same with no console erros
A38: F37 | B38: Use the interface on a small screen | C38: Compatibility | D38: In progress | E38: The interface stays usable on a smaller screen | F38: Stack running | G38: 1. Open the dashboard at 1920x1080 2. Resize to 1366x768, then to a tablet width 3. Check the navigation, the chat and the knowledge store | H38: No horizontal scrolling of the page body, no overlapping elements, and the navigation stays reachable at every width. | I38: KO | J38: Major | K38: The page scrolls horizontally. Mesuared overflow

Sheet FAS
A1: Feature ID | B1: Feature Name | C1: Category | D1: Dev status (team) | E1: Objective | F1: Prerequisites | G1: Steps | H1: Expected results | I1: RESULT | J1: Severity | K1: Feedback / anomaly (what you actually saw)
A2: F1 | B2: Sign up | C2: Critical feature | D2: Done | E2: Verify that a new user can register and access the dashboard. | F2: Application deployed and reachable (production URL or http://localhost:3000); a valid name, email and password. | G2: 1. Open the application landing page. 2. Click "Sign up" / "Register" to reach the sign-up page (/signup). 3. Fill in the form: name, email, password. 4. Submit the form. 5. Wait for the dashboard to load. 6. Reload the page to confirm the session persists. | H2: The account is created, the user is logged in and redirected to the dashboard; the user's name is displayed in the header. | I2: OK
A3: F2 | B3: Log in | C3: Critical feature | D3: Done | E3: Verify that an existing user can log in with valid credentials. | F3: A registered account (F1) and its matching credentials. | G3: 1. Open the landing page and click "Log in". 2. Enter the account email and password. 3. Submit the form. 4. Verify redirection to the dashboard. 5. Log out and retry with an incorrect password. | H3: Valid credentials grant access to the dashboard; incorrect credentials show an error and deny access. | I3: OK | K3: When the password is correct, the user can access the dashboard. When the password is incorrect, a message appears saying that the credentials are invalid, the email field is cleared, and the incorrect password remains.
A4: F3 | B4: Log out | C4: Secondary function | D4: Done | E4: Verify that the user can log out and that the session is invalidated. | F4: A logged-in session. | G4: 1. Click the account/profile menu in the header. 2. Click "Log out" / "Sign out". 3. Verify redirection to the landing page. 4. Open a protected page (e.g. /dashboard/contracts) directly in a new tab. | H4: The user is signed out; protected pages can no longer be accessed without logging in again. | I4: OK | K4: When I log out, I am redirected to the landing page: https://fas-ai.net/. When I manually enter https://fas-ai.net/dashboard/contracts, I am redirected to https://fas-ai.net/signin instead.
A5: F4 | B5: Edit account | C5: Secondary function | D5: Done | E5: Verify that the user can update their display name. | F5: A logged-in user (F2). | G5: 1. Open Settings > General. 2. Replace the display name with a new value. 3. Click "Save". 4. Reload the page. | H5: The new display name is persisted and displayed after refresh (header and settings). | I5: OK | K5: When I change my name in the settings, it is saved correctly.
A6: F5 | B6: Change password | C6: Secondary function | D6: Done | E6: Verify that the user can change their account password. | F6: A logged-in user who already has a password (F1). | G6: 1. Open Settings > Security. 2. Click "Change password". 3. Enter the current and new passwords. 4. Submit and confirm success. 5. Log out and log back in with the new password. | H6: The password is updated; login succeeds with the new password and fails with the old one. | I6: OK | K6: When I change my password and log in again, the old password no works, but the new password works correctly.
A7: F6 | B7: Set password for a guest account | C7: Secondary function | D7: Done | E7: Verify that a guest user without a password can secure their account. | F7: A guest account created through an invitation (F10/F27), with no password set. | G7: 1. As the guest, open Settings > Security. 2. Click "Set password". 3. Choose a password and submit. 4. Log out and log back in with email + password. | H7: The guest gains a usable password and can sign in with email + password afterwards. | I7: OK | K7: When I change my password and log in again, the old password no works, but the new password works correctly.
A8: F7 | B8: Delete account | C8: Critical feature | D8: Done | E8: Verify that deleting an account permanently removes access to the account and its data. | F8: A disposable account with at least one contract; logged in. | G8: 1. Open Settings > Danger Zone. 2. Type the account email in the confirmation field. 3. Confirm the deletion. 4. Verify redirection to the landing page. 5. Attempt to log in with the deleted credentials. 6. Attempt to open a previously owned contract link. | H8: Deletion is confirmed; the account can no longer log in; associated contracts and invites are no longer accessible. | I8: OK | K8: After deleting the account, it is no longer possible to access it. You are redirected to the landing page, and the previous contracts can no longer be viewed.
A9: F8 | B9: Create call | C9: Critical feature | D9: Done | E9: Verify that a user can create a new video call room. | F9: Logged in; microphone and camera available on the test device. | G9: 1. On the dashboard, click "Video Calls". 2. Click "Start New Call". 3. Enter a meeting name. 4. Create the call. | H9: A call room is created; the user reaches the pre-join/join screen and can start audio and video. | I9: OK
A10: F9 | B10: Invite people to call | C10: Critical feature | D10: Done | E10: Verify that the creator can invite registered users and guests to a call. | F10: Logged in; one extra registered account (User #2); access to a second browser session. | G10: 1. Open "Start New Call". 2. Select one registered user from the list. 3. Add a guest email address and confirm it. 4. Create the call. 5. Copy the invitation link(s) shown after creation. | H10: Registered and guest users both receive invitation links; each link is shareable and tied to the room. | I10: OK
A11: F10 | B11: Join call | C11: Critical feature | D11: Done | E11: Verify that an invited user or guest can join a call. | F11: A call created with invites (F9); an invitation link; a second browser session. | G11: 1. Open the invitation link in an incognito / second session. 2. Follow the accept flow (guest registration or sign-in). 3. Join the call. 4. Check the participant list. | H11: The participant joins the room, appears in the participant list and can exchange audio/video. | I11: OK
A12: F11 | B12: Mute audio | C12: Critical feature | D12: Done | E12: Verify that muting/unmuting updates the audio state for all participants. | F12: Two participants in an active call (F10). | G12: 1. Click the microphone button to mute. 2. Check the button/icon state. 3. Ask the other participant to confirm the mute indicator. 4. Click the microphone again to unmute. | H12: The audio is muted/unmuted instantly and the state is reflected for every participant in real time. | I12: OK
A13: F12 | B13: Turn video on/off | C13: Critical feature | D13: Done | E13: Verify that the camera can be enabled/disabled during a call. | F13: Two participants in an active call (F10). | G13: 1. Click the camera button to disable video. 2. Check that the video tile switches to a placeholder/avatar. 3. Ask the other participant to confirm the video-off state. 4. Re-enable video. | H13: The video stream toggles for all participants in real time with no delay. | I13: OK
A14: F13 | B14: Leave call | C14: Critical feature | D14: Done | E14: Verify that a participant can leave a call cleanly. | F14: An active call with two participants (F10). | G14: 1. Click "Leave" / the hang-up button. 2. Verify the user exits the room (redirection to dashboard/video-calls). 3. Ask the other participant to confirm the user no longer appears in the room. | H14: The user leaves, no ghost session remains, and the call continues for the remaining participants. | I14: OK
A15: F14 | B15: View call transcript | C15: Secondary function | D15: Done | E15: Verify that the transcription of a call is viewable. | F15: A call in which the transcriber was started during the session (see F15); accessible call history. | G15: 1. Dashboard > Video Calls. 2. Open the call detail page. 3. Click "Transcript". 4. Review the list of statements. | H15: A readable transcript is displayed, separated by participant/identity and ordered in time. | I15: OK
A16: F15 | B16: Generate call contract (AI) | C16: Critical feature | D16: Done | E16: Verify that the AI generates a contract draft from a call's transcription. | F16: A call room (F8); a second participant; the transcriber available in the call controls. | G16: 1. Start (or join) a call. 2. Start the transcription from the call controls (if not already active). 3. Talk for a few moments so the transcriber captures dialogue. 4. Click "Generate contract". 5. Wait for the generation and the success notification. 6. Open Dashboard > Contracts and check the new contract. | H16: A contract draft is generated from the call and appears in the contract list; it can be previewed and edited. | I16: OK
A17: F16 | B17: Create contract from scratch | C17: Critical feature | D17: Done | E17: Verify that a contract can be created from scratch with the builder. | F17: Logged in; contracts page accessible. | G17: 1. Dashboard > Contracts. 2. Click "New Contract" and open the contract builder. 3. Add a title and body content. 4. Add a few contract fields (text, signature, date). 5. Define participants. 6. Confirm / create the contract. | H17: The contract is created with the entered content; it appears in the contracts list and opens correctly. | I17: OK
A18: F17 | B18: Manage contract fields in builder | C18: Secondary function | D18: Done | E18: Verify that the builder allows adding and configuring fields (text, signature, date, checkbox, select, image). | F18: Contract builder opened (F16). | G18: 1. Insert a text field. 2. Configure its label and set it as required. 3. Insert a signature field and a date field. 4. Insert a checkbox and a select field. 5. Insert an image field. 6. Check the live preview. | H18: Every field type is rendered in the preview with the correct configuration and is saved with the contract. | I18: OK
A19: F18 | B19: Manage contract participants in builder | C19: Secondary function | D19: Done | E19: Verify that participants and roles can be configured in the builder. | F19: Contract builder opened (F16); a second registered user. | G19: 1. Open the participant manager. 2. Add a registered user (User #2) as a participant. 3. Assign roles and/or signing order to the fields. 4. Create the contract. 5. Open the contract's sign page to review the sequence. | H19: Participants and their roles are persisted and reflected in the signing flow. | I19: N/A | K19: ?
A20: F19 | B20: Upload contract | C20: Critical feature | D20: Done | E20: Verify that an existing contract file can be uploaded. | F20: A local contract file (PDF / DOC / DOCX / TXT); logged in. | G20: 1. Dashboard > Contracts. 2. Click "New Contract". 3. Choose "Upload Contract". 4. Select the file. 5. Submit the upload. | H20: A new contract is created from the file, appears in the list, and its preview renders correctly. | I20: OK
A21: F20 | B21: View / preview contract | C21: User interface | D21: Done | E21: Verify that a contract can be opened and previewed. | F21: At least one contract exists (F16/F19). | G21: 1. Dashboard > Contracts. 2. Open the contract card. 3. Wait for the preview to load. | H21: The contract content/preview is displayed without layout or rendering errors. | I21: OK
A22: F21 | B22: Fill contract fields | C22: Critical feature | D22: Done | E22: Verify that a participant can fill the required fields of a contract. | F22: A contract with fillable fields assigned to the tester (F17/F18). | G22: 1. Open the contract. 2. Navigate to the "Fill" step. 3. Fill the text / date / select fields. 4. Save the values. 5. Refresh the page. | H22: The values are saved, shown in the preview, and the fields are marked as completed. | I22: Partial | J22: Major | K22: When I click “Fill”, there is no option to fill anything. I can only click the “Done” button, and when I go back, the status remains the sam
A23: F22 | B23: Sign contract | C23: Critical feature | D23: Done | E23: Verify that a contract can be signed with a signature. | F23: A contract with a signature field assigned to the tester (F18). | G23: 1. Open the contract's "Sign" page. 2. Click the signature field to open the signature pad. 3. Draw the signature. 4. Save it. 5. Refresh and check the field. | H23: The signature is recorded and displayed on the contract field. | I23: Partial | J23: Major | K23: When I click “Sign”, there is no option to sign. I can only click the “Done” button, and when I go back, the status remains the same.
A24: F23 | B24: Signing progress and turn-based signing | C24: Secondary function | D24: Done | E24: Verify multi-signer, turn-based signing and progress tracking. | F24: A contract with two participants and a defined signing order (F18). | G24: 1. Sign the contract as the first signer. 2. Check the signing progress indicator. 3. Confirm the next signer's turn becomes active. 4. Sign as the second signer (second session). 5. Verify the contract reaches a finalized state once all turns are completed. | H24: Only the current signer's fields are editable; progress updates after each signature; the contract is finalized when all signatures are done. | I24: Partial | J24: Major | K24: When I click “Sign”, there is no option to sign. I can only click the “Done” button, and when I go back, the status remains the same.
A25: F24 | B25: Download signed contract | C25: Secondary function | D25: Done | E25: Verify that the completed contract can be flattened and downloaded. | F25: A filled and signed contract (F22/F23). | G25: 1. Open the contract detail page. 2. Click the "Download" / export button. 3. Check the generated file. | H25: A flattened PDF/HTML document is downloaded containing all filled values and signatures. | I25: OK
A26: F25 | B26: Delete contract | C26: Critical feature | D26: Done | E26: Verify that a contract can be deleted and access is revoked. | F26: A disposable contract (F16). | G26: 1. Open the contract detail page. 2. Click "Delete" and confirm. 3. Verify redirection to the contracts list. 4. Confirm the contract no longer appears; try opening its direct link. | H26: The contract is removed from the list and its direct link is no longer accessible. | I26: OK
A27: F26 | B27: Invite third parties to sign | C27: Critical feature | D27: Done | E27: Verify that external parties can be invited to sign a contract. | F27: A contract with participants (F16/F18); an external email address. | G27: 1. Add the external party (email) as a participant in the contract. 2. Share the signing/invitation link. 3. Open the link in another session. 4. Sign the contract as the third party. | H27: The third party accesses the contract through the link and can view and sign their assigned fields. | I27: N/A | K27: I couldn't find the share button.
A28: F27 | B28: Accept invitation as new/guest user | C28: Critical feature | D28: Done | E28: Verify that a person without an account can accept an invitation (call or contract). | F28: A valid invitation link (F9/F26) opened in a fresh session. | G28: 1. Open the invitation link in an incognito window. 2. Verify the invitation details are displayed. 3. Click "Accept" and follow the registration / sign-in flow. 4. Check redirection to the invited resource (call or contract). 5. Reopen the same link after it has been used. | H28: The guest lands on the invited resource; an already-used or invalid token shows a clear error message. | I28: N/A | K28: I couldn't find the share button.
A29: F28 | B29: Newsletter subscription | C29: User interface | D29: Done | E29: Verify that a visitor can subscribe to the newsletter. | F29: Landing page reachable. | G29: 1. Scroll to the newsletter section on the landing page. 2. Enter a name and an email. 3. Submit. 4. Check the confirmation feedback. 5. Submit the same email again. | H29: Subscription is confirmed; a duplicate/invalid email is handled gracefully with a message. | I29: KO | J29: Blocking | K29: I enter my email address, which I already have an account with, and it shows an “Internal Server Error”.
A30: F29 | B30: AI Law Assistant | C30: Critical feature | D30: In progress | E30: Verify that the AI Law Assistant answers legal questions with cited sources. | F30: Feature deployed (Sprint 9); logged-in user; AI backend configured. | G30: 1. Open the AI Law Assistant chat interface from the dashboard. 2. Ask a legal question. 3. Check the answer and its citations. 4. Continue the conversation. | H30: The assistant answers reliably and references legal sources; citations are clear; the chat history persists. | I30: N/A | K30: I cant find the AI
A31: F30 | B31: Contract templates | C31: Secondary function | D31: In progress | E31: Verify that templates (personal, sample, community) can be used to create contracts. | F31: Feature deployed (Sprint 11); logged-in user. | G31: 1. Open the templates area (personal / sample / community). 2. Browse and preview a template. 3. Create a contract from a template. 4. Save a customized version as a personal template. | H31: Templates are browsable and reusable; a contract is generated from them with the expected structure. | I31: N/A | K31: I cant find it
A32: F31 | B32: Edit contract (inputs, parties, pages) | C32: Secondary function | D32: In progress | E32: Verify that contracts can be edited after creation (inputs, parties, signature field, pages). | F32: Feature deployed (Sprint 10); an existing contract. | G32: 1. Open a contract and enter edit mode. 2. Modify text inputs. 3. Edit a signature field. 4. Add/remove a page. 5. Edit the parties. | H32: The changes are saved correctly and reflected in the preview without breaking the contract. | I32: N/A | K32: I cant find it
A33: F32 | B33: Preview generated contract in video call | C33: Secondary function | D33: In progress | E33: Verify that the contract generated from a call is previewable inside the call. | F33: Feature deployed (Sprint 10); a call with a generated contract (F15). | G33: 1. Join the call where a contract was generated. 2. Open the contract preview panel. 3. Review the generated content. | H33: The generated contract is displayed within the call UI and can be edited and finalized. | I33: N/A | K33: I cant find it
A34: F33 | B34: Sign documents without account | C34: Critical feature | D34: In progress | E34: Verify that a document can be signed without creating an account. | F34: Feature deployed (Sprint 11); a signable document shared with an external person. | G34: 1. Open the signing link without logging in. 2. Fill the required fields. 3. Sign the document. | H34: The person signs without an account; the signature is recorded for the contract owner. | I34: N/A | K34: I cant do that
A35: F34 | B35: Multi-format contracts (DOCX / JPG / PNG) | C35: Secondary function | D35: In progress | E35: Verify that DOCX, JPG and PNG contract files are supported. | F35: Feature deployed (Sprint 12); sample files in each format. | G35: 1. Upload a DOCX contract. 2. Upload a JPG contract. 3. Upload a PNG contract. 4. Open the preview of each. | H35: Each format is uploaded, rendered/previewed correctly, and can be filled and signed. | I35: OK | K35: It works
A36: F35 | B36: Website internationalization | C36: User interface | D36: In progress | E36: Verify that the application UI switches language correctly. | F36: Feature deployed (Sprint 12); at least one other language configured. | G36: 1. Open the language selector. 2. Switch to another language. 3. Navigate through the main pages. | H36: All labels and navigation are translated consistently; the choice persists across sessions. | I36: N/A | K36: I cant find it
A37: F36 | B37: Signing email notifications | C37: Secondary function | D37: In progress | E37: Verify that signers are notified by email when an action is required. | F37: Feature deployed (Sprint 9); an individual email address for the invited signer. | G37: 1. Create a contract and send an invitation to a signer. 2. Check the signer mailbox for the notification. 3. Accept and sign. 4. Check the owner mailbox for the completion notification. | H37: Email notifications are sent on invitation and on signature/completion. | I37: N/A | K37: I cant do that
A38: F37 | B38: Auto-fill contract fields | C38: Secondary function | D38: In progress | E38: Verify that contract fields can be auto-filled from known user data. | F38: Feature deployed (Sprint 9); a logged-in user with profile data. | G38: 1. Open a contract with expected fields. 2. Trigger auto-fill. 3. Review the filled values before saving. | H38: Fields are pre-filled accurately with the user's data and remain editable. | I38: N/A | K38: I cant do that
A39: F38 | B39: Error handling - duplicate email on sign-up | C39: User interface | D39: Done | E39: Verify that sign-up rejects an already registered email with a clear message. | F39: An existing account (F1). | G39: 1. Go to the sign-up page. 2. Use the existing account's email. 3. Submit the form. | H39: No new account is created; a clear error is shown and the user can correct the input. | I39: OK
A40: F39 | B40: Error handling - invalid credentials | C40: User interface | D40: Done | E40: Verify that login fails gracefully with invalid credentials. | F40: A registered account. | G40: 1. Go to the login page. 2. Enter a wrong password (or an unknown email). 3. Submit. | H40: Access is denied with a clear error message; no session is created. | I40: OK
A41: F40 | B41: Validation - signing blocked until required fields are completed | C41: User interface | D41: Done | E41: Verify that a contract cannot be signed while required fields are empty. | F41: A contract with a required text field and a signature field. | G41: 1. Open the sign page. 2. Leave a required field empty. 3. Try to save/sign. 4. Fill the field and retry. | H41: The action is blocked with a clear message while required fields are empty; it succeeds once they are filled. | I41: OK
A42: F41 | B42: Compatibility - multi-browser | C42: Compatibility | D42: Done | E42: Verify that the core flows work on the main browsers. | F42: Chrome, Firefox, Safari and Edge available; test accounts ready. | G42: 1. Run the sign-up, login, call and signing scenarios in Chrome. 2. Repeat in Firefox, Safari and Edge. | H42: Core flows behave consistently with no browser-specific breakage; the UI remains usable. | I42: N/A | K42: Due to issues with my computer, I wasn't able to test it.
A43: F42 | B43: Performance and stability (stress) | C43: Secondary function | D43: In progress | E43: Verify that the platform remains stable under load and repeated use. | F43: Feature deployed (Sprint 12); E2E and performance tooling (Playwright, Lighthouse). | G43: 1. Run repeated E2E test suites. 2. Simulate concurrent calls and contract operations. 3. Measure response times and error rates. 4. Check the logs for anomalies or crashes. | H43: No crash or blocking anomaly; response times remain within acceptable limits compared with the baseline. | I43: N/A | K43: I dont understand
A44: F43 | B44: Website accessibility | C44: User interface | D44: In progress | E44: Verify basic accessibility (keyboard navigation, contrast, ARIA). | F44: Feature deployed (Sprint 12). | G44: 1. Navigate the app using the keyboard only. 2. Run an automated accessibility check (axe / Lighthouse). 3. Check contrast and focus indicators on the key pages. | H44: Pages are navigable by keyboard, focus is visible, and no critical accessibility errors are reported. | I44: N/A | K44: I dont understand
A45: F44 | B45: SEO basics | C45: Secondary function | D45: In progress | E45: Verify that metadata (title, description, Open Graph) is present on public pages. | F45: Feature deployed (Sprint 13); public pages deployed. | G45: 1. Inspect the landing page HTML source. 2. Check the title, meta description and Open Graph tags. 3. Verify that each main route renders a relevant title. | H45: Public pages expose correct metadata and titles to search engines. | I45: OK
